Workbook

Sheet Gerencial
A1: conta | G1: Série Histórica Mensal
A2: Conta | C2: Descrição | D2: Selecionar Mês Referência
D3: 2026/10 | F3: 2026/10 | G3: 2026/09 | H3: 2026/08 | I3: 2026/07 | J3: 2026/06 | K3: 2026/05 | L3: 2026/04 | M3: 2026/03 | N3: 2026/02 | O3: 2026/01 | P3: 2025/12 | Q3: 2025/11 | R3: 2025/10 | S3: 2025/09 | T3: 2025/08 | U3: 2025/07 | V3: 2025/06 | W3: 2025/05 | X3: 2025/04 | Y3: 2025/03 | Z3: 2025/02 | AA3: 2025/01 | AB3: 2024/12 | AC3: 2024/11 | AD3: 2024/10 | AE3: 2024/09 | AF3: 2024/08 | AG3: 2024/07 | AH3: 2024/06 | AI3: 2024/05 | AJ3: 2024/04 | AK3: 2024/03 | AL3: 2024/02 | AM3: 2024/01 | AN3: 2023/12 | AO3: 2023/11
A4: Saldo Anterior | D4: {=_xlfn.XLOOKUP($D$3,INDIRECT("$F$3:$AZ3" ),INDIRECT("$F" & ROW() & ":" & "$AZ" & ROW()))} -> 6643.01 | F4: =G44 -> 6643.01 | G4: =H44 -> 6249.68 | H4: =I44 -> 2646.99 | I4: =J44 -> 2155.39 | J4: =K44 -> 1975.11 | K4: =L44 -> 1810.62 | L4: =M44 -> 6212.91 | M4: =N44 -> 5078.76 | ... AN4: =AO44 -> 1896.71 | AO4: 0
A6: 1 | C6: RECEITAS | D6: =_xlfn.XLOOKUP($D$3,INDIRECT("$F$3:$AZ3" ),INDIRECT("$F" & ROW() & ":" & "$AZ" & ROW())) -> 3058 | F6: =SUM(F7:F10) -> 3058 | G6: =SUM(G7:G10) -> 13458 | H6: =SUM(H7:H10) -> 17512 | I6: =SUM(I7:I10) -> 14232.85 | J6: =SUM(J7:J10) -> 14696.95 | K6: =SUM(K7:K10) -> 13463.1 | L6: =SUM(L7:L10) -> 10325.1 | M6: =SUM(M7:M10) -> 13892.15 | ... AO6: =SUM(AO7:AO10) -> 13368.55
A7: 1.1 | B7: Entradas | C7: Coletas | D7: =_xlfn.XLOOKUP($D$3,INDIRECT("$F$3:$AZ3" ),INDIRECT("$F" & ROW() & ":" & "$AZ" & ROW())) -> 3058 | F7: =Entradas!$E$1930 -> 3058 | G7: =Entradas!$E$1858 -> 7583 | H7: =Entradas!$E$1788 -> 11319 | I7: =Entradas!$E$1722 -> 8038 | J7: =Entradas!$E$1656 -> 9348 | K7: =Entradas!$E$1594 -> 10083.25 | L7: =Entradas!$E$1529 -> 10139 | M7: =Entradas!$E$1467 -> 10389.35 | N7: =Entradas!$E$1401 -> 8925 | O7: =Entradas!$E$1345 -> 7269 | P7: =Entradas!$E$1281 -> 9311 | Q7: =Entradas!$E$1218 -> 8539 | R7: =Entradas!$E$1155 -> 9451 | S7: =Entradas!$E$1084 -> 6597 | T7: =Entradas!$E$1020 -> 6496 | U7: =Entradas!$E$954 -> 5258.75 | V7: =Entradas!$E$887 -> 7662 | W7: =Entradas!$E$820 -> 7668 | X7: =Entradas!$E$754 -> 9178 | Y7: =Entradas!$E$691 -> 8676 | Z7: =Entradas!$E$650 -> 7615 | AA7: =Entradas!$E$613 -> 6989 | AB7: =Entradas!$E$571 -> 8645 | AC7: =Entradas!$E$529 -> 11075 | AD7: =Entradas!$E$487 -> 9447 | AE7: =Entradas!$E$443 -> 9665 | AF7: =Entradas!$E$403 -> 7955 | AG7: =Entradas!$E$362 -> 6677 | AH7: =Entradas!$E$321 -> 9133 | AI7: =Entradas!$E$280 -> 8933 | AJ7: =Entradas!$E$237 -> 8456 | AK7: =Entradas!$E$196 -> 12294 | AL7: =Entradas!$E$154 -> 7390 | AM7: =Entradas!$E$116 -> 8517 | AN7: =Entradas!$E$77 -> 10392.6 | AO7: =Entradas!$E$39 -> 12349
A8: 1.2 | C8: Intenções | D8: =_xlfn.XLOOKUP($D$3,INDIRECT("$F$3:$AZ3" ),INDIRECT("$F" & ROW() & ":" & "$AZ" & ROW())) -> 0 | F8: =Entradas!$K$1867 -> 0 | G8: =Entradas!$K$1797 -> 25 | H8: =Entradas!$K$1731 -> 43 | I8: =Entradas!$K$1665 -> 44.85 | J8: =Entradas!$K$1603 -> 98.95 | K8: =Entradas!$K$1538 -> 79.85 | L8: =Entradas!$K$1476 -> 186.1 | M8: =Entradas!$K$1411 -> 202.8 | N8: =Entradas!$K$1355 -> 91 | O8: =Entradas!$K$1292 -> 150.4 | P8: =Entradas!$K$1229 -> 265.45 | Q8: =Entradas!$K$1168 -> 363 | R8: =Entradas!$K$1098 -> 229.35 | S8: =Entradas!$K$1033 -> 117.3 | T8: =Entradas!$K$967 -> 62.75 | U8: =Entradas!$K$900 -> 143.4 | V8: =Entradas!$K$834 -> 40.85 | W8: =Entradas!$K$768 -> 332.35 | X8: =Entradas!$K$704 -> 257.7 | Y8: =Entradas!$K$663 -> 159.45 | Z8: =Entradas!$K$626 -> 259 | AA8: =Entradas!$K$584 -> 304.2 | AB8: =Entradas!$K$543 -> 255.35 | AC8: =Entradas!$K$501 -> 418.85 | AD8: =Entradas!$K$456 -> 257.05 | AE8: =Entradas!$K$416 -> 646.25 | AF8: =Entradas!$K$376 -> 251.85 | AG8: =Entradas!$K$336 -> 252.7 | AH8: =Entradas!$K$295 -> 382.95 | AI8: =Entradas!$K$254 -> 470.4 | AJ8: =Entradas!$K$213 -> 312.35 | AK8: =Entradas!$K$174 -> 400.2 | AL8: =Entradas!$K$141 -> 376.1 | AM8: =Entradas!$K$106 -> 367.95 | AN8: =Entradas!$K$65 -> 446.25 | AO8: =Entradas!$K$24 -> 319.55
A9: 1.3 | C9: Doações - Face | D9: =_xlfn.XLOOKUP($D$3,INDIRECT("$F$3:$AZ3" ),INDIRECT("$F" & ROW() & ":" & "$AZ" & ROW())) -> 0 | F9: =Entradas!$P$1866 -> 0 | G9: =Entradas!$P$1796 -> 5850 | H9: =Entradas!$P$1730 -> 6150 | I9: =Entradas!$P$1664 -> 6150 | J9: =Entradas!$P$1602 -> 5250 | K9: =Entradas!$P$1537 -> 3300 | L9: =Entradas!$P$1475 -> 0 | M9: =Entradas!$P$1410 -> 3300 | N9: =Entradas!$P$1354 -> 3597 | O9: =Entradas!$P$1291 -> 5150 | P9: =Entradas!$P$1228 -> 5200 | Q9: =Entradas!$P$1167 -> 5550 | R9: =Entradas!$P$1097 -> 3900 | S9: =Entradas!$P$1032 -> 8800 | T9: =Entradas!$P$966 -> 7500 | U9: =Entradas!$P$899 -> 7200 | V9: =Entradas!$P$827 -> 4200 | W9: =Entradas!$P$760 -> 4050 | X9: =Entradas!$P$697 -> 1500 | Y9: =Entradas!$P$663 -> 0 | Z9: =Entradas!$P$626 -> 0 | AA9: =Entradas!$P$584 -> 0 | AB9: =Entradas!$P$543 -> 0 | AC9: =Entradas!$P$494 -> 0 | AD9: =Entradas!$P$456 -> 0 | AE9: =Entradas!$P$416 -> 0 | AF9: =Entradas!$P$376 -> 0 | AG9: =Entradas!P336 -> 0 | AH9: =Entradas!P295 -> 0 | AI9: =Entradas!P254 -> 0 | AJ9: =Entradas!P213 -> 326.71 | AK9: =Entradas!$P$174 -> 0 | AL9: =Entradas!$P$141 -> 0 | AM9: =Entradas!$P$106 -> 200 | AN9: 0 | AO9: 0
A10: 1.4 | C10: Doações - Outras | D10: =_xlfn.XLOOKUP($D$3,INDIRECT("$F$3:$AZ3" ),INDIRECT("$F" & ROW() & ":" & "$AZ" & ROW())) -> 0 | F10: =Entradas!P1870 -> 0 | G10: =Entradas!P1800 -> 0 | H10: =Entradas!P1734 -> 0 | I10: =Entradas!P1668 -> 0 | J10: =Entradas!P1606 -> 0 | K10: =Entradas!P1541 -> 0 | L10: =Entradas!P1480 -> 0 | M10: =Entradas!P1415 -> 0 | N10: =Entradas!P1359 -> 0 | O10: =Entradas!$P$1297 -> 0 | P10: =Entradas!$P$1234 -> 150 | Q10: =Entradas!$P$1173 -> 0 | R10: =Entradas!$P$1103 -> 0 | S10: =Entradas!$P$1037 -> 0 | T10: =Entradas!$P$971 -> 0 | U10: =Entradas!$P$904 -> 0 | V10: =Entradas!$P$835 -> 406.15 | W10: =Entradas!$P$768 -> 0 | X10: =Entradas!$P$704 -> 0 | Y10: =Entradas!$P$656 -> 0 | Z10: =Entradas!$P$619 -> 0 | AA10: =Entradas!$P$577 -> 0 | AB10: =Entradas!$P$536 -> 0 | AC10: =Entradas!$P$501 -> 0 | AD10: =Entradas!$P$450 -> 0 | AE10: =Entradas!$P$410 -> 0 | AF10: =Entradas!$P$369 -> 0 | AG10: =Entradas!P328 -> 0 | AH10: =Entradas!P287 -> 0 | AI10: =Entradas!P244 -> 0 | AJ10: =Entradas!P203 -> 0 | AK10: =Entradas!$P$162 -> 0 | AL10: =Entradas!$P$86 -> 0 | AM10: =Entradas!$P$86 -> 0 | AN10: =Entradas!$P$65 -> 0 | AO10: =Entradas!$P$24 -> 700
A12: 2 | C12: DESPESAS | D12: =_xlfn.XLOOKUP($D$3,INDIRECT("$F$3:$AZ3" ),INDIRECT("$F" & ROW() & ":" & "$AZ" & ROW())) -> 4310 | F12: =SUM(F13:F17) -> 4310 | G12: =SUM(G13:G17) -> 13064.67 | H12: =SUM(H13:H17) -> 13909.31 | I12: =SUM(I13:I17) -> 13741.25 | J12: =SUM(J13:J17) -> 14516.67 | K12: =SUM(K13:K17) -> 13298.61 | L12: =SUM(L13:L17) -> 14727.39 | M12: =SUM(M13:M17) -> 12758 | ... AO12: =SUM(AO13:AO17) -> 11471.84
A13: 2.1 | B13: Outras | C13: Espórtulas | D13: =_xlfn.XLOOKUP($D$3,INDIRECT("$F$3:$AZ3" ),INDIRECT("$F" & ROW() & ":" & "$AZ" & ROW())) -> 4250 | F13: =SUMIFS(Despesas!$F:$F,Despesas!$A:$A,Gerencial!F$3,Despesas!$C:$C,Gerencial!$C13) -> 4250 | G13: =SUMIFS(Despesas!$F:$F,Despesas!$A:$A,Gerencial!G$3,Despesas!$C:$C,Gerencial!$C13) -> 12150 | H13: =SUMIFS(Despesas!$F:$F,Despesas!$A:$A,Gerencial!H$3,Despesas!$C:$C,Gerencial!$C13) -> 11800 | I13: =SUMIFS(Despesas!$F:$F,Despesas!$A:$A,Gerencial!I$3,Despesas!$C:$C,Gerencial!$C13) -> 11800 | J13: =SUMIFS(Despesas!$F:$F,Despesas!$A:$A,Gerencial!J$3,Despesas!$C:$C,Gerencial!$C13) -> 11000 | K13: =SUMIFS(Despesas!$F:$F,Despesas!$A:$A,Gerencial!K$3,Despesas!$C:$C,Gerencial!$C13) -> 11400 | L13: =SUMIFS(Despesas!$F:$F,Despesas!$A:$A,Gerencial!L$3,Despesas!$C:$C,Gerencial!$C13) -> 10350 | M13: =SUMIFS(Despesas!$F:$F,Despesas!$A:$A,Gerencial!M$3,Despesas!$C:$C,Gerencial!$C13) -> 11400 | ... AN13: =SUMIFS(Despesas!$F:$F,Despesas!$A:$A,Gerencial!AN$3,Despesas!$C:$C,Gerencial!$C13) -> 6720 | AO13: =SUMIFS(Despesas!$G$3:$G$287,Despesas!$A$3:$A$287,$AO$3,Despesas!$C$3:$C$287,$C13) -> 5310
A14: 2.2 | C14: Devolução de Empréstimos | D14: =_xlfn.XLOOKUP($D$3,INDIRECT("$F$3:$AZ3" ),INDIRECT("$F" & ROW() & ":" & "$AZ" & ROW())) -> 0 | F14: =SUMIFS(Despesas!$F:$F,Despesas!$A:$A,Gerencial!F$3,Despesas!$C:$C,Gerencial!$C14) -> 0 | G14: =SUMIFS(Despesas!$F:$F,Despesas!$A:$A,Gerencial!G$3,Despesas!$C:$C,Gerencial!$C14) -> 0 | H14: =SUMIFS(Despesas!$F:$F,Despesas!$A:$A,Gerencial!H$3,Despesas!$C:$C,Gerencial!$C14) -> 0 | I14: =SUMIFS(Despesas!$F:$F,Despesas!$A:$A,Gerencial!I$3,Despesas!$C:$C,Gerencial!$C14) -> 0 | J14: =SUMIFS(Despesas!$F:$F,Despesas!$A:$A,Gerencial!J$3,Despesas!$C:$C,Gerencial!$C14) -> 0 | K14: =SUMIFS(Despesas!$F:$F,Despesas!$A:$A,Gerencial!K$3,Despesas!$C:$C,Gerencial!$C14) -> 0 | L14: =SUMIFS(Despesas!$F:$F,Despesas!$A:$A,Gerencial!L$3,Despesas!$C:$C,Gerencial!$C14) -> 0 | M14: =SUMIFS(Despesas!$F:$F,Despesas!$A:$A,Gerencial!M$3,Despesas!$C:$C,Gerencial!$C14) -> 0 | ... AN14: =SUMIFS(Despesas!$F:$F,Despesas!$A:$A,Gerencial!AN$3,Despesas!$C:$C,Gerencial!$C14) -> 0 | AO14: =SUMIFS(Despesas!$G$3:$G$287,Despesas!$A$3:$A$287,$AO$3,Despesas!$C$3:$C$287,$C14) -> 700
A15: 2.3 | C15: Repasse AFC | D15: =_xlfn.XLOOKUP($D$3,INDIRECT("$F$3:$AZ3" ),INDIRECT("$F" & ROW() & ":" & "$AZ" & ROW())) -> 0 | F15: =SUMIFS(Despesas!$F:$F,Despesas!$A:$A,Gerencial!F$3,Despesas!$C:$C,Gerencial!$C15) -> 0 | G15: =SUMIFS(Despesas!$F:$F,Despesas!$A:$A,Gerencial!G$3,Despesas!$C:$C,Gerencial!$C15) -> 0 | H15: =SUMIFS(Despesas!$F:$F,Despesas!$A:$A,Gerencial!H$3,Despesas!$C:$C,Gerencial!$C15) -> 0 | I15: =SUMIFS(Despesas!$F:$F,Despesas!$A:$A,Gerencial!I$3,Despesas!$C:$C,Gerencial!$C15) -> 0 | J15: =SUMIFS(Despesas!$F:$F,Despesas!$A:$A,Gerencial!J$3,Despesas!$C:$C,Gerencial!$C15) -> 0 | K15: =SUMIFS(Despesas!$F:$F,Despesas!$A:$A,Gerencial!K$3,Despesas!$C:$C,Gerencial!$C15) -> 0 | L15: =SUMIFS(Despesas!$F:$F,Despesas!$A:$A,Gerencial!L$3,Despesas!$C:$C,Gerencial!$C15) -> 0 | M15: =SUMIFS(Despesas!$F:$F,Despesas!$A:$A,Gerencial!M$3,Despesas!$C:$C,Gerencial!$C15) -> 0 | ... AN15: =SUMIFS(Despesas!$F:$F,Despesas!$A:$A,Gerencial!AN$3,Despesas!$C:$C,Gerencial!$C15) -> 1000 | AO15: =SUMIFS(Despesas!$G$3:$G$287,Despesas!$A$3:$A$287,$AO$3,Despesas!$C$3:$C$287,$C15) -> 4000
A16: 2.4 | C16: Repasse Paróquia São Vicente | D16: =_xlfn.XLOOKUP($D$3,INDIRECT("$F$3:$AZ3" ),INDIRECT("$F" & ROW() & ":" & "$AZ" & ROW())) -> 0 | F16: =SUMIFS(Despesas!$F:$F,Despesas!$A:$A,Gerencial!F$3,Despesas!$C:$C,Gerencial!$C16) -> 0 | G16: =SUMIFS(Despesas!$F:$F,Despesas!$A:$A,Gerencial!G$3,Despesas!$C:$C,Gerencial!$C16) -> 0 | H16: =SUMIFS(Despesas!$F:$F,Despesas!$A:$A,Gerencial!H$3,Despesas!$C:$C,Gerencial!$C16) -> 0 | I16: =SUMIFS(Despesas!$F:$F,Despesas!$A:$A,Gerencial!I$3,Despesas!$C:$C,Gerencial!$C16) -> 0 | J16: =SUMIFS(Despesas!$F:$F,Despesas!$A:$A,Gerencial!J$3,Despesas!$C:$C,Gerencial!$C16) -> 2150 | K16: =SUMIFS(Despesas!$F:$F,Despesas!$A:$A,Gerencial!K$3,Despesas!$C:$C,Gerencial!$C16) -> 0 | L16: =SUMIFS(Despesas!$F:$F,Despesas!$A:$A,Gerencial!L$3,Despesas!$C:$C,Gerencial!$C16) -> 1965 | M16: =SUMIFS(Despesas!$F:$F,Despesas!$A:$A,Gerencial!M$3,Despesas!$C:$C,Gerencial!$C16) -> 0 | ... AN16: =SUMIFS(Despesas!$F:$F,Despesas!$A:$A,Gerencial!AN$3,Despesas!$C:$C,Gerencial!$C16) -> 625 | AO16: =SUMIFS(Despesas!$G$3:$G$287,Despesas!$A$3:$A$287,$AO$3,Despesas!$C$3:$C$287,$C16) -> 0
A17: 2.5 | C17: Itens de Consumo | D17: =_xlfn.XLOOKUP($D$3,INDIRECT("$F$3:$AZ3" ),INDIRECT("$F" & ROW() & ":" & "$AZ" & ROW())) -> 60 | F17: =SUM(F18:F40) -> 60 | G17: =SUM(G18:G40) -> 914.67 | H17: =SUM(H18:H40) -> 2109.31 | I17: =SUM(I18:I40) -> 1941.25 | J17: =SUM(J18:J40) -> 1366.67 | K17: =SUM(K18:K40) -> 1898.61 | L17: =SUM(L18:L40) -> 2412.39 | M17: =SUM(M18:M40) -> 1358 | ... AO17: =SUM(AO18:AO40) -> 1461.84
A18: 2.5.1 | B18: Itens de Consumo | C18: Decoração Capela | D18: =_xlfn.XLOOKUP($D$3,INDIRECT("$F$3:$AZ3" ),INDIRECT("$F" & ROW() & ":" & "$AZ" & ROW())) -> 0 | F18: =SUMIFS(Despesas!$F:$F,Despesas!$A:$A,Gerencial!F$3,Despesas!$C:$C,Gerencial!$C18) -> 0 | G18: =SUMIFS(Despesas!$F:$F,Despesas!$A:$A,Gerencial!G$3,Despesas!$C:$C,Gerencial!$C18) -> 0 | H18: =SUMIFS(Despesas!$F:$F,Despesas!$A:$A,Gerencial!H$3,Despesas!$C:$C,Gerencial!$C18) -> 29.99 | I18: =SUMIFS(Despesas!$F:$F,Despesas!$A:$A,Gerencial!I$3,Despesas!$C:$C,Gerencial!$C18) -> 386 | J18: =SUMIFS(Despesas!$F:$F,Despesas!$A:$A,Gerencial!J$3,Despesas!$C:$C,Gerencial!$C18) -> 563.05 | K18: =SUMIFS(Despesas!$F:$F,Despesas!$A:$A,Gerencial!K$3,Despesas!$C:$C,Gerencial!$C18) -> 0 | L18: =SUMIFS(Despesas!$F:$F,Despesas!$A:$A,Gerencial!L$3,Despesas!$C:$C,Gerencial!$C18) -> 0 | M18: =SUMIFS(Despesas!$F:$F,Despesas!$A:$A,Gerencial!M$3,Despesas!$C:$C,Gerencial!$C18) -> 194.75 | ... AN18: =SUMIFS(Despesas!$F:$F,Despesas!$A:$A,Gerencial!AN$3,Despesas!$C:$C,Gerencial!$C18) -> 163.4 | AO18: =SUMIFS(Despesas!$G$3:$G$287,Despesas!$A$3:$A$287,$AO$3,Despesas!$C$3:$C$287,$C18) -> 119.9
A19: 2.5.2 | C19: Vinho | D19: =_xlfn.XLOOKUP($D$3,INDIRECT("$F$3:$AZ3" ),INDIRECT("$F" & ROW() & ":" & "$AZ" & ROW())) -> 0 | F19: =SUMIFS(Despesas!$F:$F,Despesas!$A:$A,Gerencial!F$3,Despesas!$C:$C,Gerencial!$C19) -> 0 | G19: =SUMIFS(Despesas!$F:$F,Despesas!$A:$A,Gerencial!G$3,Despesas!$C:$C,Gerencial!$C19) -> 0 | H19: =SUMIFS(Despesas!$F:$F,Despesas!$A:$A,Gerencial!H$3,Despesas!$C:$C,Gerencial!$C19) -> 269.4 | I19: =SUMIFS(Despesas!$F:$F,Despesas!$A:$A,Gerencial!I$3,Despesas!$C:$C,Gerencial!$C19) -> 0 | J19: =SUMIFS(Despesas!$F:$F,Despesas!$A:$A,Gerencial!J$3,Despesas!$C:$C,Gerencial!$C19) -> 0 | K19: =SUMIFS(Despesas!$F:$F,Despesas!$A:$A,Gerencial!K$3,Despesas!$C:$C,Gerencial!$C19) -> 264 | L19: =SUMIFS(Despesas!$F:$F,Despesas!$A:$A,Gerencial!L$3,Despesas!$C:$C,Gerencial!$C19) -> 0 | M19: =SUMIFS(Despesas!$F:$F,Despesas!$A:$A,Gerencial!M$3,Despesas!$C:$C,Gerencial!$C19) -> 0 | ... AN19: =SUMIFS(Despesas!$F:$F,Despesas!$A:$A,Gerencial!AN$3,Despesas!$C:$C,Gerencial!$C19) -> 0 | AO19: =SUMIFS(Despesas!$G$3:$G$287,Despesas!$A$3:$A$287,$AO$3,Despesas!$C$3:C$287,$C19) -> 0
A20: 2.5.3 | C20: Partículas | D20: =_xlfn.XLOOKUP($D$3,INDIRECT("$F$3:$AZ3" ),INDIRECT("$F" & ROW() & ":" & "$AZ" & ROW())) -> 0 | F20: =SUMIFS(Despesas!$F:$F,Despesas!$A:$A,Gerencial!F$3,Despesas!$C:$C,Gerencial!$C20) -> 0 | G20: =SUMIFS(Despesas!$F:$F,Despesas!$A:$A,Gerencial!G$3,Despesas!$C:$C,Gerencial!$C20) -> 320 | H20: =SUMIFS(Despesas!$F:$F,Despesas!$A:$A,Gerencial!H$3,Despesas!$C:$C,Gerencial!$C20) -> 703 | I20: =SUMIFS(Despesas!$F:$F,Despesas!$A:$A,Gerencial!I$3,Despesas!$C:$C,Gerencial!$C20) -> 511 | J20: =SUMIFS(Despesas!$F:$F,Despesas!$A:$A,Gerencial!J$3,Despesas!$C:$C,Gerencial!$C20) -> 472.9 | K20: =SUMIFS(Despesas!$F:$F,Despesas!$A:$A,Gerencial!K$3,Despesas!$C:$C,Gerencial!$C20) -> 400 | L20: =SUMIFS(Despesas!$F:$F,Despesas!$A:$A,Gerencial!L$3,Despesas!$C:$C,Gerencial!$C20) -> 280 | M20: =SUMIFS(Despesas!$F:$F,Despesas!$A:$A,Gerencial!M$3,Despesas!$C:$C,Gerencial!$C20) -> 619.6 | ... AN20: =SUMIFS(Despesas!$F:$F,Despesas!$A:$A,Gerencial!AN$3,Despesas!$C:$C,Gerencial!$C20) -> 269 | AO20: =SUMIFS(Despesas!$G$3:$G$287,Despesas!$A$3:$A$287,$AO$3,Despesas!$C$3:C$287,$C20) -> 245
A21: 2.5.4 | C21: Água | D21: =_xlfn.XLOOKUP($D$3,INDIRECT("$F$3:$AZ3" ),INDIRECT("$F" & ROW() & ":" & "$AZ" & ROW())) -> 0 | F21: =SUMIFS(Despesas!$F:$F,Despesas!$A:$A,Gerencial!F$3,Despesas!$C:$C,Gerencial!$C21) -> 0 | G21: =SUMIFS(Despesas!$F:$F,Despesas!$A:$A,Gerencial!G$3,Despesas!$C:$C,Gerencial!$C21) -> 102 | H21: =SUMIFS(Despesas!$F:$F,Despesas!$A:$A,Gerencial!H$3,Despesas!$C:$C,Gerencial!$C21) -> 51 | I21: =SUMIFS(Despesas!$F:$F,Despesas!$A:$A,Gerencial!I$3,Despesas!$C:$C,Gerencial!$C21) -> 85 | J21: =SUMIFS(Despesas!$F:$F,Despesas!$A:$A,Gerencial!J$3,Despesas!$C:$C,Gerencial!$C21) -> 99 | K21: =SUMIFS(Despesas!$F:$F,Despesas!$A:$A,Gerencial!K$3,Despesas!$C:$C,Gerencial!$C21) -> 62 | L21: =SUMIFS(Despesas!$F:$F,Despesas!$A:$A,Gerencial!L$3,Despesas!$C:$C,Gerencial!$C21) -> 90 | M21: =SUMIFS(Despesas!$F:$F,Despesas!$A:$A,Gerencial!M$3,Despesas!$C:$C,Gerencial!$C21) -> 30 | ... AN21: =SUMIFS(Despesas!$F:$F,Despesas!$A:$A,Gerencial!AN$3,Despesas!$C:$C,Gerencial!$C21) -> 48 | AO21: =SUMIFS(Despesas!$G$3:$G$287,Despesas!$A$3:$A$287,$AO$3,Despesas!$C$3:C$287,$C21) -> 12
A22: 2.5.5 | C22: Descartáveis (Copos, pratos) | D22: =_xlfn.XLOOKUP($D$3,INDIRECT("$F$3:$AZ3" ),INDIRECT("$F" & ROW() & ":" & "$AZ" & ROW())) -> 60 | F22: =SUMIFS(Despesas!$F:$F,Despesas!$A:$A,Gerencial!F$3,Despesas!$C:$C,Gerencial!$C22) -> 60 | G22: =SUMIFS(Despesas!$F:$F,Despesas!$A:$A,Gerencial!G$3,Despesas!$C:$C,Gerencial!$C22) -> 0 | H22: =SUMIFS(Despesas!$F:$F,Despesas!$A:$A,Gerencial!H$3,Despesas!$C:$C,Gerencial!$C22) -> 306.42 | I22: =SUMIFS(Despesas!$F:$F,Despesas!$A:$A,Gerencial!I$3,Despesas!$C:$C,Gerencial!$C22) -> 0 | J22: =SUMIFS(Despesas!$F:$F,Despesas!$A:$A,Gerencial!J$3,Despesas!$C:$C,Gerencial!$C22) -> 0 | K22: =SUMIFS(Despesas!$F:$F,Despesas!$A:$A,Gerencial!K$3,Despesas!$C:$C,Gerencial!$C22) -> 0 | L22: =SUMIFS(Despesas!$F:$F,Despesas!$A:$A,Gerencial!L$3,Despesas!$C:$C,Gerencial!$C22) -> 0 | M22: =SUMIFS(Despesas!$F:$F,Despesas!$A:$A,Gerencial!M$3,Despesas!$C:$C,Gerencial!$C22) -> 0 | ... AN22: =SUMIFS(Despesas!$F:$F,Despesas!$A:$A,Gerencial!AN$3,Despesas!$C:$C,Gerencial!$C22) -> 0 | AO22: =SUMIFS(Despesas!$G$3:$G$287,Despesas!$A$3:$A$287,$AO$3,Despesas!$C$3:C$287,$C22) -> 125.94
A23: 2.5.6 | C23: Papel toalha | D23: =_xlfn.XLOOKUP($D$3,INDIRECT("$F$3:$AZ3" ),INDIRECT("$F" & ROW() & ":" & "$AZ" & ROW())) -> 0 | F23: =SUMIFS(Despesas!$F:$F,Despesas!$A:$A,Gerencial!F$3,Despesas!$C:$C,Gerencial!$C23) -> 0 | G23: =SUMIFS(Despesas!$F:$F,Despesas!$A:$A,Gerencial!G$3,Despesas!$C:$C,Gerencial!$C23) -> 33.52 | H23: =SUMIFS(Despesas!$F:$F,Despesas!$A:$A,Gerencial!H$3,Despesas!$C:$C,Gerencial!$C23) -> 37.45 | I23: =SUMIFS(Despesas!$F:$F,Despesas!$A:$A,Gerencial!I$3,Despesas!$C:$C,Gerencial!$C23) -> 55.05 | J23: =SUMIFS(Despesas!$F:$F,Despesas!$A:$A,Gerencial!J$3,Despesas!$C:$C,Gerencial!$C23) -> 0 | K23: =SUMIFS(Despesas!$F:$F,Despesas!$A:$A,Gerencial!K$3,Despesas!$C:$C,Gerencial!$C23) -> 0 | L23: =SUMIFS(Despesas!$F:$F,Despesas!$A:$A,Gerencial!L$3,Despesas!$C:$C,Gerencial!$C23) -> 0 | M23: =SUMIFS(Despesas!$F:$F,Despesas!$A:$A,Gerencial!M$3,Despesas!$C:$C,Gerencial!$C23) -> 13.58 | ... AN23: =SUMIFS(Despesas!$F:$F,Despesas!$A:$A,Gerencial!AN$3,Despesas!$C:$C,Gerencial!$C23) -> 19.73 | AO23: =SUMIFS(Despesas!$G$3:$G$287,Despesas!$A$3:$A$287,$AO$3,Despesas!$C$3:C$287,$C23) -> 21.46
A24: 2.5.7 | C24: Cheirinho ( anti-môfo) | D24: =_xlfn.XLOOKUP($D$3,INDIRECT("$F$3:$AZ3" ),INDIRECT("$F" & ROW() & ":" & "$AZ" & ROW())) -> 0 | F24: =SUMIFS(Despesas!$F:$F,Despesas!$A:$A,Gerencial!F$3,Despesas!$C:$C,Gerencial!$C24) -> 0 | G24: =SUMIFS(Despesas!$F:$F,Despesas!$A:$A,Gerencial!G$3,Despesas!$C:$C,Gerencial!$C24) -> 0 | H24: =SUMIFS(Despesas!$F:$F,Despesas!$A:$A,Gerencial!H$3,Despesas!$C:$C,Gerencial!$C24) -> 0 | I24: =SUMIFS(Despesas!$F:$F,Despesas!$A:$A,Gerencial!I$3,Despesas!$C:$C,Gerencial!$C24) -> 0 | J24: =SUMIFS(Despesas!$F:$F,Despesas!$A:$A,Gerencial!J$3,Despesas!$C:$C,Gerencial!$C24) -> 0 | K24: =SUMIFS(Despesas!$F:$F,Despesas!$A:$A,Gerencial!K$3,Despesas!$C:$C,Gerencial!$C24) -> 0 | L24: =SUMIFS(Despesas!$F:$F,Despesas!$A:$A,Gerencial!L$3,Despesas!$C:$C,Gerencial!$C24) -> 0 | M24: =SUMIFS(Despesas!$F:$F,Despesas!$A:$A,Gerencial!M$3,Despesas!$C:$C,Gerencial!$C24) -> 0 | ... AN24: =SUMIFS(Despesas!$F:$F,Despesas!$A:$A,Gerencial!AN$3,Despesas!$C:$C,Gerencial!$C24) -> 0 | AO24: =SUMIFS(Despesas!$G$3:$G$287,Despesas!$A$3:$A$287,$AO$3,Despesas!$C$3:C$287,$C24) -> 0
A25: 2.5.8 | C25: Incenso | D25: =_xlfn.XLOOKUP($D$3,INDIRECT("$F$3:$AZ3" ),INDIRECT("$F" & ROW() & ":" & "$AZ" & ROW())) -> 0 | F25: =SUMIFS(Despesas!$F:$F,Despesas!$A:$A,Gerencial!F$3,Despesas!$C:$C,Gerencial!$C25) -> 0 | G25: =SUMIFS(Despesas!$F:$F,Despesas!$A:$A,Gerencial!G$3,Despesas!$C:$C,Gerencial!$C25) -> 0 | H25: =SUMIFS(Despesas!$F:$F,Despesas!$A:$A,Gerencial!H$3,Despesas!$C:$C,Gerencial!$C25) -> 0 | I25: =SUMIFS(Despesas!$F:$F,Despesas!$A:$A,Gerencial!I$3,Despesas!$C:$C,Gerencial!$C25) -> 51.6 | J25: =SUMIFS(Despesas!$F:$F,Despesas!$A:$A,Gerencial!J$3,Despesas!$C:$C,Gerencial!$C25) -> 0 | K25: =SUMIFS(Despesas!$F:$F,Despesas!$A:$A,Gerencial!K$3,Despesas!$C:$C,Gerencial!$C25) -> 0 | L25: =SUMIFS(Despesas!$F:$F,Despesas!$A:$A,Gerencial!L$3,Despesas!$C:$C,Gerencial!$C25) -> 0 | M25: =SUMIFS(Despesas!$F:$F,Despesas!$A:$A,Gerencial!M$3,Despesas!$C:$C,Gerencial!$C25) -> 0 | ... AN25: =SUMIFS(Despesas!$F:$F,Despesas!$A:$A,Gerencial!AN$3,Despesas!$C:$C,Gerencial!$C25) -> 0 | AO25: =SUMIFS(Despesas!$G$3:$G$287,Despesas!$A$3:$A$287,$AO$3,Despesas!$C$3:C$287,$C25) -> 0
A26: 2.5.9 | C26: Carvão Tablete | D26: =_xlfn.XLOOKUP($D$3,INDIRECT("$F$3:$AZ3" ),INDIRECT("$F" & ROW() & ":" & "$AZ" & ROW())) -> 0 | F26: =SUMIFS(Despesas!$F:$F,Despesas!$A:$A,Gerencial!F$3,Despesas!$C:$C,Gerencial!$C26) -> 0 | G26: =SUMIFS(Despesas!$F:$F,Despesas!$A:$A,Gerencial!G$3,Despesas!$C:$C,Gerencial!$C26) -> 0 | H26: =SUMIFS(Despesas!$F:$F,Despesas!$A:$A,Gerencial!H$3,Despesas!$C:$C,Gerencial!$C26) -> 14.99 | I26: =SUMIFS(Despesas!$F:$F,Despesas!$A:$A,Gerencial!I$3,Despesas!$C:$C,Gerencial!$C26) -> 46.5 | J26: =SUMIFS(Despesas!$F:$F,Despesas!$A:$A,Gerencial!J$3,Despesas!$C:$C,Gerencial!$C26) -> 0 | K26: =SUMIFS(Despesas!$F:$F,Despesas!$A:$A,Gerencial!K$3,Despesas!$C:$C,Gerencial!$C26) -> 16.79 | L26: =SUMIFS(Despesas!$F:$F,Despesas!$A:$A,Gerencial!L$3,Despesas!$C:$C,Gerencial!$C26) -> 0 | M26: =SUMIFS(Despesas!$F:$F,Despesas!$A:$A,Gerencial!M$3,Despesas!$C:$C,Gerencial!$C26) -> 0 | ... AN26: =SUMIFS(Despesas!$F:$F,Despesas!$A:$A,Gerencial!AN$3,Despesas!$C:$C,Gerencial!$C26) -> 0 | AO26: =SUMIFS(Despesas!$G$3:$G$287,Despesas!$A$3:$A$287,$AO$3,Despesas!$C$3:C$287,$C26) -> 30
A27: 2.5.10 | C27: Velas ( Altar, Santíssimo e diárias ) | D27: =_xlfn.XLOOKUP($D$3,INDIRECT("$F$3:$AZ3" ),INDIRECT("$F" & ROW() & ":" & "$AZ" & ROW())) -> 0 | F27: =SUMIFS(Despesas!$F:$F,Despesas!$A:$A,Gerencial!F$3,Despesas!$C:$C,Gerencial!$C27) -> 0 | G27: =SUMIFS(Despesas!$F:$F,Despesas!$A:$A,Gerencial!G$3,Despesas!$C:$C,Gerencial!$C27) -> 272.25 | H27: =SUMIFS(Despesas!$F:$F,Despesas!$A:$A,Gerencial!H$3,Despesas!$C:$C,Gerencial!$C27) -> 0 | I27: =SUMIFS(Despesas!$F:$F,Despesas!$A:$A,Gerencial!I$3,Despesas!$C:$C,Gerencial!$C27) -> 0 | J27: =SUMIFS(Despesas!$F:$F,Despesas!$A:$A,Gerencial!J$3,Despesas!$C:$C,Gerencial!$C27) -> 0 | K27: =SUMIFS(Despesas!$F:$F,Despesas!$A:$A,Gerencial!K$3,Despesas!$C:$C,Gerencial!$C27) -> 0 | L27: =SUMIFS(Despesas!$F:$F,Despesas!$A:$A,Gerencial!L$3,Despesas!$C:$C,Gerencial!$C27) -> 0 | M27: =SUMIFS(Despesas!$F:$F,Despesas!$A:$A,Gerencial!M$3,Despesas!$C:$C,Gerencial!$C27) -> 340.4 | ... AN27: =SUMIFS(Despesas!$F:$F,Despesas!$A:$A,Gerencial!AN$3,Despesas!$C:$C,Gerencial!$C27) -> 98.7 | AO27: =SUMIFS(Despesas!$G$3:$G$287,Despesas!$A$3:$A$287,$AO$3,Despesas!$C$3:C$287,$C27) -> 319.83
A28: 2.5.11 | C28: Mangas vidro | D28: =_xlfn.XLOOKUP($D$3,INDIRECT("$F$3:$AZ3" ),INDIRECT("$F" & ROW() & ":" & "$AZ" & ROW())) -> 0 | F28: =SUMIFS(Despesas!$F:$F,Despesas!$A:$A,Gerencial!F$3,Despesas!$C:$C,Gerencial!$C28) -> 0 | G28: =SUMIFS(Despesas!$F:$F,Despesas!$A:$A,Gerencial!G$3,Despesas!$C:$C,Gerencial!$C28) -> 0 | H28: =SUMIFS(Despesas!$F:$F,Despesas!$A:$A,Gerencial!H$3,Despesas!$C:$C,Gerencial!$C28) -> 0 | I28: =SUMIFS(Despesas!$F:$F,Despesas!$A:$A,Gerencial!I$3,Despesas!$C:$C,Gerencial!$C28) -> 0 | J28: =SUMIFS(Despesas!$F:$F,Despesas!$A:$A,Gerencial!J$3,Despesas!$C:$C,Gerencial!$C28) -> 0 | K28: =SUMIFS(Despesas!$F:$F,Despesas!$A:$A,Gerencial!K$3,Despesas!$C:$C,Gerencial!$C28) -> 0 | L28: =SUMIFS(Despesas!$F:$F,Despesas!$A:$A,Gerencial!L$3,Despesas!$C:$C,Gerencial!$C28) -> 0 | M28: =SUMIFS(Despesas!$F:$F,Despesas!$A:$A,Gerencial!M$3,Despesas!$C:$C,Gerencial!$C28) -> 0 | ... AN28: =SUMIFS(Despesas!$F:$F,Despesas!$A:$A,Gerencial!AN$3,Despesas!$C:$C,Gerencial!$C28) -> 0 | AO28: =SUMIFS(Despesas!$G$3:$G$287,Despesas!$A$3:$A$287,$AO$3,Despesas!$C$3:C$287,$C28) -> 0
A29: 2.5.12 | C29: Lavanderia | D29: =_xlfn.XLOOKUP($D$3,INDIRECT("$F$3:$AZ3" ),INDIRECT("$F" & ROW() & ":" & "$AZ" & ROW())) -> 0 | F29: =SUMIFS(Despesas!$F:$F,Despesas!$A:$A,Gerencial!F$3,Despesas!$C:$C,Gerencial!$C29) -> 0 | G29: =SUMIFS(Despesas!$F:$F,Despesas!$A:$A,Gerencial!G$3,Despesas!$C:$C,Gerencial!$C29) -> 151 | H29: =SUMIFS(Despesas!$F:$F,Despesas!$A:$A,Gerencial!H$3,Despesas!$C:$C,Gerencial!$C29) -> 511.51 | I29: =SUMIFS(Despesas!$F:$F,Despesas!$A:$A,Gerencial!I$3,Despesas!$C:$C,Gerencial!$C29) -> 233.11 | J29: =SUMIFS(Despesas!$F:$F,Despesas!$A:$A,Gerencial!J$3,Despesas!$C:$C,Gerencial!$C29) -> 231.72 | K29: =SUMIFS(Despesas!$F:$F,Despesas!$A:$A,Gerencial!K$3,Despesas!$C:$C,Gerencial!$C29) -> 0 | L29: =SUMIFS(Despesas!$F:$F,Despesas!$A:$A,Gerencial!L$3,Despesas!$C:$C,Gerencial!$C29) -> 372.3 | M29: =SUMIFS(Despesas!$F:$F,Despesas!$A:$A,Gerencial!M$3,Despesas!$C:$C,Gerencial!$C29) -> 123 | ... AN29: =SUMIFS(Despesas!$F:$F,Despesas!$A:$A,Gerencial!AN$3,Despesas!$C:$C,Gerencial!$C29) -> 457.87 | AO29: =SUMIFS(Despesas!$G$3:$G$287,Despesas!$A$3:$A$287,$AO$3,Despesas!$C$3:C$287,$C29) -> 387.23
A30: 2.5.13 | C30: Alfaias litúrgicas ( corporal e sanguíneo ) | D30: =_xlfn.XLOOKUP($D$3,INDIRECT("$F$3:$AZ3" ),INDIRECT("$F" & ROW() & ":" & "$AZ" & ROW())) -> 0 | F30: =SUMIFS(Despesas!$F:$F,Despesas!$A:$A,Gerencial!F$3,Despesas!$C:$C,Gerencial!$C30) -> 0 | G30: =SUMIFS(Despesas!$F:$F,Despesas!$A:$A,Gerencial!G$3,Despesas!$C:$C,Gerencial!$C30) -> 0 | H30: =SUMIFS(Despesas!$F:$F,Despesas!$A:$A,Gerencial!H$3,Despesas!$C:$C,Gerencial!$C30) -> 0 | I30: =SUMIFS(Despesas!$F:$F,Despesas!$A:$A,Gerencial!I$3,Despesas!$C:$C,Gerencial!$C30) -> 563.2 | J30: =SUMIFS(Despesas!$F:$F,Despesas!$A:$A,Gerencial!J$3,Despesas!$C:$C,Gerencial!$C30) -> 0 | K30: =SUMIFS(Despesas!$F:$F,Despesas!$A:$A,Gerencial!K$3,Despesas!$C:$C,Gerencial!$C30) -> 0 | L30: =SUMIFS(Despesas!$F:$F,Despesas!$A:$A,Gerencial!L$3,Despesas!$C:$C,Gerencial!$C30) -> 0 | M30: =SUMIFS(Despesas!$F:$F,Despesas!$A:$A,Gerencial!M$3,Despesas!$C:$C,Gerencial!$C30) -> 0 | ... AN30: =SUMIFS(Despesas!$F:$F,Despesas!$A:$A,Gerencial!AN$3,Despesas!$C:$C,Gerencial!$C30) -> 0 | AO30: =SUMIFS(Despesas!$G$3:$G$287,Despesas!$A$3:$A$287,$AO$3,Despesas!$C$3:C$287,$C30) -> 0
... A40: 2.5.23 | C40: Livro Diretório | D40: =_xlfn.XLOOKUP($D$3,INDIRECT("$F$3:$AZ3" ),INDIRECT("$F" & ROW() & ":" & "$AZ" & ROW())) -> 0 | F40: =SUMIFS(Despesas!$F:$F,Despesas!$A:$A,Gerencial!F$3,Despesas!$C:$C,Gerencial!$C40) -> 0 | G40: =SUMIFS(Despesas!$F:$F,Despesas!$A:$A,Gerencial!G$3,Despesas!$C:$C,Gerencial!$C40) -> 0 | H40: =SUMIFS(Despesas!$F:$F,Despesas!$A:$A,Gerencial!H$3,Despesas!$C:$C,Gerencial!$C40) -> 0 | I40: =SUMIFS(Despesas!$F:$F,Despesas!$A:$A,Gerencial!I$3,Despesas!$C:$C,Gerencial!$C40) -> 0 | J40: =SUMIFS(Despesas!$F:$F,Despesas!$A:$A,Gerencial!J$3,Despesas!$C:$C,Gerencial!$C40) -> 0 | K40: =SUMIFS(Despesas!$F:$F,Despesas!$A:$A,Gerencial!K$3,Despesas!$C:$C,Gerencial!$C40) -> 0 | L40: =SUMIFS(Despesas!$F:$F,Despesas!$A:$A,Gerencial!L$3,Despesas!$C:$C,Gerencial!$C40) -> 0 | M40: =SUMIFS(Despesas!$F:$F,Despesas!$A:$A,Gerencial!M$3,Despesas!$C:$C,Gerencial!$C40) -> 0 | ... AN40: =SUMIFS(Despesas!$F:$F,Despesas!$A:$A,Gerencial!AN$3,Despesas!$C:$C,Gerencial!$C40) -> 0 | AO40: =SUMIFS(Despesas!$G$3:$G$287,Despesas!$A$3:$A$287,$AO$3,Despesas!$C$3:C$287,$C40) -> 42.5
A42: Saldo Operacional (Receitas - Despesas) | D42: =_xlfn.XLOOKUP($D$3,INDIRECT("$F$3:$AZ3" ),INDIRECT("$F" & ROW() & ":" & "$AZ" & ROW())) -> 5391.01 | F42: =F$4+F$6-F$12 -> 5391.01 | G42: =G$4+G$6-G$12 -> 6643.01 | H42: =H$4+H$6-H$12 -> 6249.68 | I42: =I$4+I$6-I$12 -> 2646.99 | J42: =J$4+J$6-J$12 -> 2155.39 | K42: =K$4+K$6-K$12 -> 1975.11 | L42: =L$4+L$6-L$12 -> 1810.62 | M42: =M$4+M$6-M$12 -> 6212.91 | ... AO42: =AO$4+AO$6-AO$12 -> 1896.71
A43: Compromissos A Pagar (Sacerdotes) | D43: =_xlfn.XLOOKUP($D$3,INDIRECT("$F$3:$AZ3" ),INDIRECT("$F" & ROW() & ":" & "$AZ" & ROW())) -> 11550 | F43: =Sacerdotes!$Q$2110 -> 11550 | G43: =Sacerdotes!$Q$2030 -> 0 | H43: =Sacerdotes!$Q$1955 -> 0 | I43: =Sacerdotes!$Q$1879 -> 0 | J43: =Sacerdotes!$Q$1802 -> 0 | K43: =Sacerdotes!$Q$1727 -> 0 | L43: =Sacerdotes!$Q$1659 -> 0 | M43: =Sacerdotes!$Q$1585 -> 0 | N43: =Sacerdotes!$Q$1520 -> 0 | O43: =Sacerdotes!$Q$1448 -> 0 | P43: =Sacerdotes!$Q$1375 -> 0 | Q43: =Sacerdotes!$Q$1305 -> 0 | R43: =Sacerdotes!$Q$1228 -> 0 | S43: =Sacerdotes!$Q$1156 -> 0 | T43: =Sacerdotes!$Q$1084 -> 0 | U43: =Sacerdotes!$Q$1011 -> 0 | V43: =Sacerdotes!$Q$941 -> 0 | W43: =Sacerdotes!$Q$869 -> 0 | X43: =Sacerdotes!$Q$800 -> 0 | Y43: =Sacerdotes!$Q$754 -> 0 | Z43: =Sacerdotes!$Q$711 -> 0 | AA43: =Sacerdotes!$Q$665 -> 0 | AB43: =Sacerdotes!$Q$618 -> 0 | AC43: =Sacerdotes!$Q$571 -> 0 | AD43: =Sacerdotes!$Q$521 -> 0 | AE43: =Sacerdotes!$Q$475 -> 0 | AF43: =Sacerdotes!$Q$428 -> 0 | AG43: =Sacerdotes!Q381 -> 0 | AH43: =Sacerdotes!Q335 -> 0 | AI43: =Sacerdotes!Q287 -> 0 | AJ43: =Sacerdotes!Q241 -> 0 | AK43: =Sacerdotes!Q200 -> 0 | AL43: =Sacerdotes!Q160 -> 0 | AM43: =SUMIFS(Sacerdotes!$F$90:$F$133,Sacerdotes!$H$90:$H$133,FALSE) -> 0 | AN43: =SUMIFS(Sacerdotes!$F$45:$F$87,Sacerdotes!$H$45:$H$87,FALSE) -> 0 | AO43: =SUMIFS(Sacerdotes!$F$3:$F$42,Sacerdotes!$H$3:$H$42,FALSE) -> 0
A44: Saldo Final | D44: =_xlfn.XLOOKUP($D$3,INDIRECT("$F$3:$AZ3" ),INDIRECT("$F" & ROW() & ":" & "$AZ" & ROW())) -> -6158.99 | F44: =F$42-F$43 -> -6158.99 | G44: =G$42-G$43 -> 6643.01 | H44: =H$42-H$43 -> 6249.68 | I44: =I$42-I$43 -> 2646.99 | J44: =J$42-J$43 -> 2155.39 | K44: =K$42-K$43 -> 1975.11 | L44: =L$42-L$43 -> 1810.62 | M44: =M$42-M$43 -> 6212.91 | ... AO44: =AO$42-AO$43 -> 1896.71

Sheet Dashboard
A1: Opção 1 | G1: Selecione o Ano | I1: 2026
B2: Resumo por Período | R2: Período | T2: Receitas | U2: Despesas | V2: Saldo | X2: Período | Z2: Coletas | AA2: Espórtulas | AB2: Saldo
B3: =R2 -> Período | C3: =T2 -> Receitas | D3: =U2 -> Despesas | E3: =V2 -> Saldo | R3: 2023 | S3: 45231 | T3: =Gerencial!$AO$6 -> 13368.55 | U3: =Gerencial!$AO$12 -> 11471.84 | V3: =Gerencial!$AO$42 -> 1896.71 | X3: 2023 | Y3: 45231 | Z3: =Gerencial!$AO$7 -> 12349 | AA3: =Gerencial!$AO$13 -> 5310 | AB3: =Z3-AA3 -> 7039
B4: =IFERROR(__xludf.DUMMYFUNCTION("FILTER($S$3:$V1002,YEAR($S$3:$S1002)=$I$1)"),46023.0) -> 46023 | C4: =IFERROR(__xludf.DUMMYFUNCTION("""COMPUTED_VALUE"""),12569.4) -> 12569.4 | D4: =IFERROR(__xludf.DUMMYFUNCTION("""COMPUTED_VALUE"""),13328.74) -> 13328.74 | E4: =IFERROR(__xludf.DUMMYFUNCTION("""COMPUTED_VALUE"""),4207.660000000009) -> 4207.66 | S4: 45261 | T4: =Gerencial!$AN$6 -> 10838.85 | U4: =Gerencial!$AN$12 -> 9674.37 | V4: =Gerencial!$AN$42 -> 3061.19 | Y4: 45261 | Z4: =Gerencial!$AN$7 -> 10392.6 | AA4: =Gerencial!$AN$13 -> 6720 | AB4: =Z4-AA4 -> 3672.6
B5: =IFERROR(__xludf.DUMMYFUNCTION("""COMPUTED_VALUE"""),46054.0) -> 46054 | C5: =IFERROR(__xludf.DUMMYFUNCTION("""COMPUTED_VALUE"""),12613.0) -> 12613 | D5: =IFERROR(__xludf.DUMMYFUNCTION("""COMPUTED_VALUE"""),11741.9) -> 11741.9 | E5: =IFERROR(__xludf.DUMMYFUNCTION("""COMPUTED_VALUE"""),5078.760000000011) -> 5078.76 | R5: 2024 | S5: 45292 | T5: =Gerencial!$AM$6 -> 9084.95 | U5: =Gerencial!$AM$12 -> 8932.05 | V5: =Gerencial!$AM$42 -> 3214.09 | X5: 2024 | Y5: 45292 | Z5: =Gerencial!$AM$7 -> 8517 | AA5: =Gerencial!$AM$13 -> 6210 | AB5: =Z5-AA5 -> 2307
B6: =IFERROR(__xludf.DUMMYFUNCTION("""COMPUTED_VALUE"""),46082.0) -> 46082 | C6: =IFERROR(__xludf.DUMMYFUNCTION("""COMPUTED_VALUE"""),13892.15) -> 13892.15 | D6: =IFERROR(__xludf.DUMMYFUNCTION("""COMPUTED_VALUE"""),12758.0) -> 12758 | E6: =IFERROR(__xludf.DUMMYFUNCTION("""COMPUTED_VALUE"""),6212.910000000011) -> 6212.91 | S6: 45323 | T6: =Gerencial!$AL$6 -> 7766.1 | U6: =Gerencial!$AL$12 -> 7973.87 | V6: =Gerencial!$AL$42 -> 3006.32 | Y6: 45323 | Z6: =Gerencial!$AL$7 -> 7390 | AA6: =Gerencial!$AL$13 -> 5600 | AB6: =Z6-AA6 -> 1790
B7: =IFERROR(__xludf.DUMMYFUNCTION("""COMPUTED_VALUE"""),46113.0) -> 46113 | C7: =IFERROR(__xludf.DUMMYFUNCTION("""COMPUTED_VALUE"""),10325.1) -> 10325.1 | D7: =IFERROR(__xludf.DUMMYFUNCTION("""COMPUTED_VALUE"""),14727.39) -> 14727.39 | E7: =IFERROR(__xludf.DUMMYFUNCTION("""COMPUTED_VALUE"""),1810.62000000001) -> 1810.62 | S7: 45352 | T7: =Gerencial!$AK$6 -> 12694.2 | U7: =Gerencial!$AK$12 -> 11251.34 | V7: =Gerencial!$AK$42 -> 4449.18 | Y7: 45352 | Z7: =Gerencial!$AK$7 -> 12294 | AA7: =Gerencial!$AK$13 -> 6900 | AB7: =Z7-AA7 -> 5394
B8: =IFERROR(__xludf.DUMMYFUNCTION("""COMPUTED_VALUE"""),46143.0) -> 46143 | C8: =IFERROR(__xludf.DUMMYFUNCTION("""COMPUTED_VALUE"""),13463.1) -> 13463.1 | D8: =IFERROR(__xludf.DUMMYFUNCTION("""COMPUTED_VALUE"""),13298.61) -> 13298.61 | E8: =IFERROR(__xludf.DUMMYFUNCTION("""COMPUTED_VALUE"""),1975.1100000000097) -> 1975.11 | S8: 45383 | T8: =Gerencial!$AJ$6 -> 9095.06 | U8: =Gerencial!$AJ$12 -> 9702.14 | V8: =Gerencial!$AJ$42 -> 3842.1 | Y8: 45383 | Z8: =Gerencial!$AJ$7 -> 8456 | AA8: =Gerencial!$AJ$13 -> 7200 | AB8: =Z8-AA8 -> 1256
B9: =IFERROR(__xludf.DUMMYFUNCTION("""COMPUTED_VALUE"""),46174.0) -> 46174 | C9: =IFERROR(__xludf.DUMMYFUNCTION("""COMPUTED_VALUE"""),14696.95) -> 14696.95 | D9: =IFERROR(__xludf.DUMMYFUNCTION("""COMPUTED_VALUE"""),14516.67) -> 14516.67 | E9: =IFERROR(__xludf.DUMMYFUNCTION("""COMPUTED_VALUE"""),2155.390000000012) -> 2155.39 | S9: 45413 | T9: =Gerencial!$AI$6 -> 9403.4 | U9: =Gerencial!$AI$12 -> 9819.12 | V9: =Gerencial!$AI$42 -> 3426.38 | Y9: 45413 | Z9: =Gerencial!$AI$7 -> 8933 | AA9: =Gerencial!$AI$13 -> 7400 | AB9: =Z9-AA9 -> 1533
B10: =IFERROR(__xludf.DUMMYFUNCTION("""COMPUTED_VALUE"""),46204.0) -> 46204 | C10: =IFERROR(__xludf.DUMMYFUNCTION("""COMPUTED_VALUE"""),14232.85) -> 14232.85 | D10: =IFERROR(__xludf.DUMMYFUNCTION("""COMPUTED_VALUE"""),13741.25) -> 13741.25 | E10: =IFERROR(__xludf.DUMMYFUNCTION("""COMPUTED_VALUE"""),2646.9900000000125) -> 2646.99 | S10: 45444 | T10: =Gerencial!$AH$6 -> 9515.95 | U10: =Gerencial!$AH$12 -> 10475.73 | V10: =Gerencial!$AH$42 -> 2466.6 | Y10: 45444 | Z10: =Gerencial!$AH$7 -> 9133 | AA10: =Gerencial!$AH$13 -> 7350 | AB10: =Z10-AA10 -> 1783
B11: =IFERROR(__xludf.DUMMYFUNCTION("""COMPUTED_VALUE"""),46235.0) -> 46235 | C11: =IFERROR(__xludf.DUMMYFUNCTION("""COMPUTED_VALUE"""),17512.0) -> 17512 | D11: =IFERROR(__xludf.DUMMYFUNCTION("""COMPUTED_VALUE"""),13909.31) -> 13909.31 | E11: =IFERROR(__xludf.DUMMYFUNCTION("""COMPUTED_VALUE"""),6249.680000000013) -> 6249.68 | S11: 45474 | T11: =Gerencial!$AG$6 -> 6929.7 | U11: =Gerencial!$AG$12 -> 8315.75 | V11: =Gerencial!$AG$42 -> 1080.55 | Y11: 45474 | Z11: =Gerencial!$AG$7 -> 6677 | AA11: =Gerencial!$AG$13 -> 7150 | AB11: =Z11-AA11 -> -473
B12: =IFERROR(__xludf.DUMMYFUNCTION("""COMPUTED_VALUE"""),46266.0) -> 46266 | C12: =IFERROR(__xludf.DUMMYFUNCTION("""COMPUTED_VALUE"""),13458.0) -> 13458 | D12: =IFERROR(__xludf.DUMMYFUNCTION("""COMPUTED_VALUE"""),13064.67) -> 13064.67 | E12: =IFERROR(__xludf.DUMMYFUNCTION("""COMPUTED_VALUE"""),6643.010000000015) -> 6643.01 | S12: 45505 | T12: =Gerencial!$AF$6 -> 8206.85 | U12: =Gerencial!$AF$12 -> 8155.99 | V12: =Gerencial!$AF$42 -> 1131.41 | Y12: 45505 | Z12: =Gerencial!$AF$7 -> 7955 | AA12: =Gerencial!$AF$13 -> 7007.2 | AB12: =Z12-AA12 -> 947.8
B13: =IFERROR(__xludf.DUMMYFUNCTION("""COMPUTED_VALUE"""),46296.0) -> 46296 | C13: =IFERROR(__xludf.DUMMYFUNCTION("""COMPUTED_VALUE"""),3058.0) -> 3058 | D13: =IFERROR(__xludf.DUMMYFUNCTION("""COMPUTED_VALUE"""),4310.0) -> 4310 | E13: =IFERROR(__xludf.DUMMYFUNCTION("""COMPUTED_VALUE"""),5391.010000000015) -> 5391.01 | S13: 45536 | T13: =Gerencial!$AE$6 -> 10311.25 | U13: =Gerencial!$AE$12 -> 8564.75 | V13: =Gerencial!$AE$42 -> 2877.91 | Y13: 45536 | Z13: =Gerencial!$AE$7 -> 9665 | AA13: =Gerencial!$AE$13 -> 6950 | AB13: =Z13-AA13 -> 2715
B14: =IFERROR(__xludf.DUMMYFUNCTION("""COMPUTED_VALUE"""),46327.0) -> 46327 | S14: 45566 | T14: =Gerencial!$AD$6 -> 9704.05 | U14: =Gerencial!$AD$12 -> 12451.86 | V14: =Gerencial!$AD$42 -> 130.1 | Y14: 45566 | Z14: =Gerencial!$AD$7 -> 9447 | AA14: =Gerencial!$AD$13 -> 7150 | AB14: =Z14-AA14 -> 2297
B15: =IFERROR(__xludf.DUMMYFUNCTION("""COMPUTED_VALUE"""),46357.0) -> 46357 | S15: 45597 | T15: =Gerencial!$AC$6 -> 11493.85 | U15: =Gerencial!$AC$12 -> 9428.78 | V15: =Gerencial!$AC$42 -> 2195.17 | Y15: 45597 | Z15: =Gerencial!$AC$7 -> 11075 | AA15: =Gerencial!$AC$13 -> 6850 | AB15: =Z15-AA15 -> 4225
B16: Total | C16: =SUM(C4:C15) -> 125820.55 | D16: =SUM(D4:D15) -> 125396.54 | E16: =C16-D16 -> 424.01 | S16: 45627 | T16: =Gerencial!$AB$6 -> 8900.35 | U16: =Gerencial!$AB$12 -> 8669.53 | V16: =Gerencial!$AB$42 -> 2425.99 | Y16: 45627 | Z16: =Gerencial!$AB$7 -> 8645 | AA16: =Gerencial!$AB$13 -> 6600 | AB16: =Z16-AA16 -> 2045
R17: 2025 | S17: 45658 | T17: =Gerencial!$AA$6 -> 7293.2 | U17: =Gerencial!$AA$12 -> 7458.12 | V17: =Gerencial!$AA$42 -> 2261.07 | X17: 2025 | Y17: 45658 | Z17: =Gerencial!$AA$7 -> 6989 | AA17: =Gerencial!$AA$13 -> 6900 | AB17: =Z17-AA17 -> 89
S18: 45689 | T18: =Gerencial!$Z$6 -> 7874 | U18: =Gerencial!$Z$12 -> 8622.88 | V18: =Gerencial!$Z$42 -> 1512.19 | Y18: 45689 | Z18: =Gerencial!$Z$7 -> 7615 | AA18: =Gerencial!$Z$13 -> 5900 | AB18: =Z18-AA18 -> 1715
B19: =Gerencial!D3 -> 2026/10 | S19: 45717 | T19: =Gerencial!$Y$6 -> 8835.45 | U19: =Gerencial!$Y$12 -> 7485.02 | V19: =Gerencial!$Y$42 -> 2862.62 | Y19: 45717 | Z19: =Gerencial!$Y$7 -> 8676 | AA19: =Gerencial!$Y$13 -> 6500 | AB19: =Z19-AA19 -> 2176
S20: 45748 | T20: =Gerencial!$X$6 -> 10935.7 | U20: =Gerencial!$X$12 -> 11055.31 | V20: =Gerencial!$X$42 -> 2743.01 | Y20: 45748 | Z20: =Gerencial!$X$7 -> 9178 | AA20: =Gerencial!$X$13 -> 7650 | AB20: =Z20-AA20 -> 1528
S21: 45778 | T21: =Gerencial!$W$6 -> 12050.35 | U21: =Gerencial!$W$12 -> 12750.15 | V21: =Gerencial!$W$42 -> 2043.21 | Y21: 45778 | Z21: =Gerencial!$W$7 -> 7668 | AA21: =Gerencial!$W$13 -> 11100 | AB21: =Z21-AA21 -> -3432
S22: 45809 | T22: =Gerencial!$V$6 -> 12309 | U22: =Gerencial!$V$12 -> 12427.72 | V22: =Gerencial!$V$42 -> 1924.49 | Y22: 45809 | Z22: =Gerencial!$V$7 -> 7662 | AA22: =Gerencial!$V$13 -> 10750 | AB22: =Z22-AA22 -> -3088
S23: 45839 | T23: =Gerencial!$U$6 -> 12602.15 | U23: =Gerencial!$U$12 -> 13318.58 | V23: =Gerencial!$U$42 -> 1208.06 | Y23: 45839 | Z23: =Gerencial!$U$7 -> 5258.75 | AA23: =Gerencial!$U$13 -> 11100 | AB23: =Z23-AA23 -> -5841.25
S24: 45870 | T24: =Gerencial!$T$6 -> 14058.75 | U24: =Gerencial!$T$12 -> 12759.19 | V24: =Gerencial!$T$42 -> 2507.62 | Y24: 45870 | Z24: =Gerencial!$T$7 -> 6496 | AA24: =Gerencial!$T$13 -> 10950 | AB24: =Z24-AA24 -> -4454
B25: DEMONSTRATIVO DO MÊS | S25: 45901 | T25: =Gerencial!$S$6 -> 15514.3 | U25: =Gerencial!$S$12 -> 12693.73 | V25: =Gerencial!$S$42 -> 5328.19 | Y25: 45901 | Z25: =Gerencial!$S$7 -> 6597 | AA25: =Gerencial!$S$13 -> 10950 | AB25: =Z25-AA25 -> -4353
S26: 45931 | T26: =Gerencial!$R$6 -> 13580.35 | U26: =Gerencial!$R$12 -> 15823.48 | V26: =Gerencial!$R$42 -> 3085.06 | Y26: 45931 | Z26: =Gerencial!$R$7 -> 9451 | AA26: =Gerencial!$R$13 -> 11650 | AB26: =Z26-AA26 -> -2199
S27: 45962 | T27: =Gerencial!$Q$6 -> 14452 | U27: =Gerencial!$Q$12 -> 11820.5 | V27: =Gerencial!$Q$42 -> 5716.56 | Y27: 45962 | Z27: =Gerencial!$Q$7 -> 8539 | AA27: =Gerencial!$Q$13 -> 10650 | AB27: =Z27-AA27 -> -2111
S28: 45992 | T28: =Gerencial!$P$6 -> 14926.45 | U28: =Gerencial!$P$12 -> 15676.01 | V28: =Gerencial!$P$42 -> 4967 | Y28: 45992 | Z28: =Gerencial!$P$7 -> 9311 | AA28: =Gerencial!$P$13 -> 11050 | AB28: =Z28-AA28 -> -1739
R29: 2026 | S29: 46023 | T29: =Gerencial!$O$6 -> 12569.4 | U29: =Gerencial!$O$12 -> 13328.74 | V29: =Gerencial!$O$42 -> 4207.66 | X29: 2026 | Y29: 46023 | Z29: =Gerencial!$O$7 -> 7269 | AA29: =Gerencial!$O$13 -> 11200 | AB29: =Z29-AA29 -> -3931
S30: 46054 | T30: =Gerencial!$N$6 -> 12613 | U30: =Gerencial!$N$12 -> 11741.9 | V30: =Gerencial!$N$42 -> 5078.76 | Y30: 46054 | Z30: =Gerencial!$N$7 -> 8925 | AA30: =Gerencial!$N$13 -> 10100 | AB30: =Z30-AA30 -> -1175
S31: 46082 | T31: =Gerencial!$M$6 -> 13892.15 | U31: =Gerencial!$M$12 -> 12758 | V31: =Gerencial!$M$42 -> 6212.91 | Y31: 46082 | Z31: =Gerencial!$M$7 -> 10389.35 | AA31: =Gerencial!$M$13 -> 11400 | AB31: =Z31-AA31 -> -1010.65
S32: 46113 | T32: =Gerencial!$L$6 -> 10325.1 | U32: =Gerencial!$L$12 -> 14727.39 | V32: =Gerencial!$L$42 -> 1810.62 | Y32: 46113 | Z32: =Gerencial!$L$7 -> 10139 | AA32: =Gerencial!$L$13 -> 10350 | AB32: =Z32-AA32 -> -211
S33: 46143 | T33: =Gerencial!$K$6 -> 13463.1 | U33: =Gerencial!$K$12 -> 13298.61 | V33: =Gerencial!$K$42 -> 1975.11 | Y33: 46143 | Z33: =Gerencial!$K$7 -> 10083.25 | AA33: =Gerencial!$K$13 -> 11400 | AB33: =Z33-AA33 -> -1316.75
S34: 46174 | T34: =Gerencial!$J$6 -> 14696.95 | U34: =Gerencial!$J$12 -> 14516.67 | V34: =Gerencial!$J$42 -> 2155.39 | Y34: 46174 | Z34: =Gerencial!$J$7 -> 9348 | AA34: =Gerencial!$J$13 -> 11000 | AB34: =Z34-AA34 -> -1652
S35: 46204 | T35: =Gerencial!$I$6 -> 14232.85 | U35: =Gerencial!$I$12 -> 13741.25 | V35: =Gerencial!$I$42 -> 2646.99 | Y35: 46204 | Z35: =Gerencial!$I$7 -> 8038 | AA35: =Gerencial!$I$13 -> 11800 | AB35: =Z35-AA35 -> -3762
S36: 46235 | T36: =Gerencial!$H$6 -> 17512 | U36: =Gerencial!$H$12 -> 13909.31 | V36: =Gerencial!$H$42 -> 6249.68 | Y36: 46235
S37: 46266 | T37: =Gerencial!$G$6 -> 13458 | U37: =Gerencial!$G$12 -> 13064.67 | V37: =Gerencial!$G$42 -> 6643.01 | Y37: 46266
S38: 46296 | T38: =Gerencial!$F$6 -> 3058 | U38: =Gerencial!$F$12 -> 4310 | V38: =Gerencial!$F$42 -> 5391.01 | Y38: 46296
S39: 46327 | Y39: 46327
S40: 46357 | Y40: 46357
B58: Comparativo Coleta x Espórtula
B59: Período | C59: Coleta | D59: Espórtula | E59: Saldo
B60: =IFERROR(__xludf.DUMMYFUNCTION("FILTER($Y$3:$AB1002,YEAR($Y$3:$Y1002)=$I$1)"),46023.0) -> 46023 | C60: =IFERROR(__xludf.DUMMYFUNCTION("""COMPUTED_VALUE"""),7269.0) -> 7269 | D60: =IFERROR(__xludf.DUMMYFUNCTION("""COMPUTED_VALUE"""),11200.0) -> 11200 | E60: =IFERROR(__xludf.DUMMYFUNCTION("""COMPUTED_VALUE"""),-3931.0) -> -3931
B61: =IFERROR(__xludf.DUMMYFUNCTION("""COMPUTED_VALUE"""),46054.0) -> 46054 | C61: =IFERROR(__xludf.DUMMYFUNCTION("""COMPUTED_VALUE"""),8925.0) -> 8925 | D61: =IFERROR(__xludf.DUMMYFUNCTION("""COMPUTED_VALUE"""),10100.0) -> 10100 | E61: =IFERROR(__xludf.DUMMYFUNCTION("""COMPUTED_VALUE"""),-1175.0) -> -1175
B62: =IFERROR(__xludf.DUMMYFUNCTION("""COMPUTED_VALUE"""),46082.0) -> 46082 | C62: =IFERROR(__xludf.DUMMYFUNCTION("""COMPUTED_VALUE"""),10389.35) -> 10389.35 | D62: =IFERROR(__xludf.DUMMYFUNCTION("""COMPUTED_VALUE"""),11400.0) -> 11400 | E62: =IFERROR(__xludf.DUMMYFUNCTION("""COMPUTED_VALUE"""),-1010.6499999999996) -> -1010.65
B63: =IFERROR(__xludf.DUMMYFUNCTION("""COMPUTED_VALUE"""),46113.0) -> 46113 | C63: =IFERROR(__xludf.DUMMYFUNCTION("""COMPUTED_VALUE"""),10139.0) -> 10139 | D63: =IFERROR(__xludf.DUMMYFUNCTION("""COMPUTED_VALUE"""),10350.0) -> 10350 | E63: =IFERROR(__xludf.DUMMYFUNCTION("""COMPUTED_VALUE"""),-211.0) -> -211
B64: =IFERROR(__xludf.DUMMYFUNCTION("""COMPUTED_VALUE"""),46143.0) -> 46143 | C64: =IFERROR(__xludf.DUMMYFUNCTION("""COMPUTED_VALUE"""),10083.25) -> 10083.25 | D64: =IFERROR(__xludf.DUMMYFUNCTION("""COMPUTED_VALUE"""),11400.0) -> 11400 | E64: =IFERROR(__xludf.DUMMYFUNCTION("""COMPUTED_VALUE"""),-1316.75) -> -1316.75
B65: =IFERROR(__xludf.DUMMYFUNCTION("""COMPUTED_VALUE"""),46174.0) -> 46174 | C65: =IFERROR(__xludf.DUMMYFUNCTION("""COMPUTED_VALUE"""),9348.0) -> 9348 | D65: =IFERROR(__xludf.DUMMYFUNCTION("""COMPUTED_VALUE"""),11000.0) -> 11000 | E65: =IFERROR(__xludf.DUMMYFUNCTION("""COMPUTED_VALUE"""),-1652.0) -> -1652
B66: =IFERROR(__xludf.DUMMYFUNCTION("""COMPUTED_VALUE"""),46204.0) -> 46204 | C66: =IFERROR(__xludf.DUMMYFUNCTION("""COMPUTED_VALUE"""),8038.0) -> 8038 | D66: =IFERROR(__xludf.DUMMYFUNCTION("""COMPUTED_VALUE"""),11800.0) -> 11800 | E66: =IFERROR(__xludf.DUMMYFUNCTION("""COMPUTED_VALUE"""),-3762.0) -> -3762
B67: =IFERROR(__xludf.DUMMYFUNCTION("""COMPUTED_VALUE"""),46235.0) -> 46235
B68: =IFERROR(__xludf.DUMMYFUNCTION("""COMPUTED_VALUE"""),46266.0) -> 46266
B69: =IFERROR(__xludf.DUMMYFUNCTION("""COMPUTED_VALUE"""),46296.0) -> 46296
B70: =IFERROR(__xludf.DUMMYFUNCTION("""COMPUTED_VALUE"""),46327.0) -> 46327
B71: =IFERROR(__xludf.DUMMYFUNCTION("""COMPUTED_VALUE"""),46357.0) -> 46357
B72: Total | C72: =SUM(C60:C71) -> 64191.6 | D72: =SUM(D60:D71) -> 77250 | E72: =C72-D72 -> -13058.4

Sheet Entradas
A2: COLETAS | I2: INTENÇÕES | N2: EMPRÉSTIMOS
A3: Data | B3: Dia | C3: Turno | D3: Celebrante | E3: Valor coleta | F3: Responsáveis | G3: Observação | I3: Data | J3: Dia da semana | K3: Valor | L3: Observação | N3: Data | O3: Dia da semana | P3: Valor | Q3: Observação
A4: 45231 | B4: =A4 -> 45231 | C4: Manhã | D4: Monsenhor Idelfonso | E4: 145 | F4: Oscar e Milena | I4: 45233 | J4: =I4 -> 45233 | K4: 98.65 | N4: 45231 | O4: Quarta-feira | P4: 700 | Q4: Nilda pgto espórtulas dias 3 e 5
A5: 45232 | B5: =A5 -> 45232 | C5: Manhã | D5: Monsenhor Idelfonso | E5: 665 | F5: Wilson e Aucilene | I5: 45238 | J5: =I5 -> 45238 | K5: 17.7 | O5: =N5
A6: 45233 | B6: =A6 -> 45233 | C6: Manhã | D6: Padre Marcos | E6: 200 | F6: João Paulo e Neide | I6: 45244 | J6: =I6 -> 45244 | K6: 37.6 | O6: =N6
C7: Noite | D7: Padre Josieldo | E7: 257 | F7: Vieira e Wandson | G7: Missa das famílias | I7: 45245 | J7: =I7 -> 45245 | K7: 42.1 | O7: =N7
A8: 45235 | B8: =A8 -> 45235 | C8: Manhã | D8: Padre Josieldo | E8: 650 | F8: Wandson e Ailton | I8: 45254 | J8: =I8 -> 45254 | K8: 38
A9: 45235 | B9: =A9 -> 45235 | C9: Noite | D9: Padre Pafael Maciel | E9: 674 | F9: Ana Lúcia e Alberto | I9: 45256 | J9: =I9 -> 45256 | K9: 39
A10: 45236 | B10: =A10 -> 45236 | C10: Manhã | D10: Monsenhor Idelfonso | E10: 52 | F10: Ana Lúcia e Oscar | I10: 45259 | J10: =I10 -> 45259 | K10: 46.5
A11: 45237 | B11: =A11 -> 45237 | C11: Manhã | D11: Padre Marcos | E11: 185 | F11: Vieira e Clediana
A12: 45238 | B12: =A12 -> 45238 | C12: Manhã | D12: Monsenhor Idelfonso | E12: 155 | F12: Neide e Tânia
A13: 45239 | B13: =A13 -> 45239 | C13: Manhã | D13: Monsenhor Idelfonso | E13: 91 | F13: Sávio e Albaniza
A14: 45240 | B14: =A14 -> 45240 | C14: Manhã | D14: Padre Josieldo | E14: 113 | F14: João Paulo e Neide
A15: 10 | B15: sexta-feira | C15: Noite | D15: Padre Virgínio | E15: 2750 | F15: Milena, Ailton, Liliane, Eduardo, Adaila | G15: Missa da Crisma
A16: 11 | B16: sábado | C16: Noite | D16: Padre Santino Sacramento | E16: 669 | F16: Oscar, Vieira, Albaniza | G16: Missa da Catequese
A17: 45242 | B17: =A17 -> 45242 | C17: Manhã | D17: Padre Josieldo | E17: 620 | F17: Wilson Camelo e Eduardo
C18: Noite | D18: Padre Watson | E18: 650 | F18: Wandson e Lidia
A19: 45243 | B19: =A19 -> 45243 | C19: Manhã | D19: Monsenhor Idelfonso | E19: 200 | F19: Ana Lúcia e Alaide
A20: 45244 | B20: =A20 -> 45244 | C20: Manhã | D20: Marcos | E20: 90 | F20: Clediana e Tânia
A21: 45245 | B21: =A21 -> 45245 | C21: Manhã | D21: Monsenhor Idelfonso | E21: 239 | F21: Vieira e Myrtes
A22: 45246 | B22: =A22 -> 45246 | C22: Manhã | D22: Monsenhor Idelfonso | E22: 118 | F22: Ailton e Milena
A23: 45247 | B23: =A23 -> 45247 | C23: Manhã | D23: Padre Josieldo | E23: 90 | F23: João Paulo e Alda
A24: 45248 | B24: =A24 -> 45248 | C24: Manhã | D24: N/A | E24: 0 | F24: N/A | I24: Total | K24: =SUM(K4:K23) -> 319.55 | N24: Total | P24: =SUM(P4:P23) -> 700
A25: 45249 | B25: =A25 -> 45249 | C25: Manhã | D25: Padre Josieldo | E25: 610 | F25: Marquinhos
C26: Noite | D26: Padre Paulo | E26: 920 | F26: Jarbas e Eduardo
A27: 45250 | B27: =A27 -> 45250 | C27: Manhã | D27: Monsenhor Idelfonso | E27: 113 | F27: Ana Lucia e Alaide
A28: 45251 | B28: =A28 -> 45251 | C28: Manhã | E28: 70 | F28: Clediana e Alda
A29: 45252 | B29: =A29 -> 45252 | C29: Manhã | D29: Monsenhor Idelfonso | E29: 134 | F29: Sávio e Tânia
A30: 45253 | B30: =A30 -> 45253 | C30: Manhã | D30: Monsenhor Idelfonso | E30: 47 | F30: Sávio e Milena
A31: 45254 | B31: =A31 -> 45254 | C31: Manhã | D31: Padre Josieldo | E31: 61 | F31: João Paulo e Tânia
A32: 45255 | B32: =A32 -> 45255 | C32: Manhã | D32: Padre Diego Juaçaba | E32: 120 | F32: Pe Diego Juaçaba | G32: Missa Célia Nóbrega
A33: 45256 | B33: =A33 -> 45256 | C33: Manhã | D33: Frei Ricardo Régis | E33: 594 | F33: Neidinha e Vieira
C34: Noite | D34: Padre Diego Juaçaba | E34: 664 | F34: Lena e Eduardo
A35: 45257 | B35: =A35 -> 45257 | C35: Manhã | D35: Monsenhor Idelfonso | E35: 55 | F35: Ana Lúcia e Alaide
A36: 45258 | B36: =A36 -> 45258 | C36: Manhã | D36: Monsenhor Idelfonso | E36: 120 | F36: Clediana e Sávio
A37: 45259 | B37: =A37 -> 45259 | C37: Manhã | D37: Padre Diego Juaçaba | E37: 107 | F37: Ailton e Liliane
A38: 45260 | B38: =A38 -> 45260 | C38: Manhã | D38: Padre Diego Juaçaba | E38: 121 | F38: Vieira e Ana Lúcia
A39: Total | E39: =SUM(E4:E38) -> 12349
A41: Dezembro/2023
A42: COLETAS | I42: INTENÇÕES | N42: EMPRÉSTIMOS
A43: Data | B43: Dia | C43: Turno | D43: Celebrante | E43: Valor coleta | F43: Responsáveis | G43: Observação | I43: Data | J43: Dia da semana | K43: Valor | L43: Observação | N43: Data | O43: Dia da semana | P43: Valor | Q43: Observação
A44: 45261 | B44: =A44 -> 45261 | C44: Manhã | D44: Pe Marcos | E44: 170 | F44: Oscar e Neide | I44: 45264 | J44: =I44 -> 45264 | K44: 19.75
A45: 45263 | B45: =A45 -> 45263 | C45: Manhã | D45: Pe Edvânio | E45: 561 | F45: Marcos e Vieira | I45: 45266 | J45: =I45 -> 45266 | K45: 39 | O45: =N45
C46: Noite | D46: Monsenhor Idelfonso | E46: 585 | F46: Lidia e Myrtes | I46: 45268 | J46: =I46 -> 45268 | K46: 29.55
A47: 45264 | B47: =A47 -> 45264 | C47: Noite | E47: 90 | F47: Liliane e Ana Lúcia | I47: 45272 | J47: =I47 -> 45272 | K47: 59.7 | O47: =N47
A48: 45265 | B48: =A48 -> 45265 | C48: Manhã | D48: Pe Marcos | E48: 72 | F48: Alda e Clediana | I48: 45277 | J48: =I48 -> 45277 | K48: 58.3
A49: 45266 | B49: =A49 -> 45266 | C49: Noite | D49: Monsenhor Idelfonso | E49: 179 | F49: Ailton e Liliane | I49: 45280 | J49: =I49 -> 45280 | K49: 47.5
A50: 45267 | B50: =A50 -> 45267 | C50: Manhã | D50: Monsenhor Idelfonso | E50: 69 | F50: Vieira e Sávio | I50: 45286 | J50: =I50 -> 45286 | K50: 72.45
A51: 45268 | B51: =A51 -> 45268 | C51: Manhã | D51: Pe Marcos | E51: 255 | F51: João Paulo e Edna | I51: 45288 | J51: =I51 -> 45288 | K51: 120
A52: 45270 | B52: =A52 -> 45270 | C52: Manhã | D52: Pe Diego Félix | E52: 637 | F52: Wandson e Aucilente
C53: Noite | E53: 1072 | F53: Adaila e Eduardo
A54: 45271 | B54: =A54 -> 45271 | C54: Manhã | D54: Monsenhor Idelfonso | E54: 120 | F54: Ana Lúcia e Alaide
A55: 45272 | B55: =A55 -> 45272 | C55: Noite | D55: Pe Marcos | E55: 150 | F55: Clediana e Alda
A56: 45273 | B56: =A56 -> 45273 | C56: Manhã | D56: Monsenhor Idelfonso | E56: 113 | F56: João Paulo e Neide
C57: Noite | D57: Pe Neto | E57: 290.6 | F57: Williams Correia
A58: 45274 | B58: =A58 -> 45274 | C58: Manhã | D58: Monsenhor Idelfonso | E58: 112 | F58: Milena e Sávio
A59: 45275 | B59: =A59 -> 45275 | C59: Noite | D59: Pe Marcos | E59: 132 | F59: João Paulo e Vieira
A60: 45277 | B60: =A60 -> 45277 | C60: Manhã | D60: Pe. Josieldo | E60: 625 | F60: Vieira
C61: Noite | D61: Frei Ricardo Régis | E61: 751 | F61: Wandson e Eduardo
A62: 45278 | B62: =A62 -> 45278 | C62: Manhã | D62: Monsenhor Idelfonso | E62: 102 | F62: Bernardo e Ana Lúcia
A63: 45279 | B63: =A63 -> 45279 | C63: Manhã | D63: Pe Marcos | E63: 104 | F63: Clediana e Sávio
A64: 45280 | B64: =A64 -> 45280 | C64: Manhã | D64: Monsenhor Idelfonso | E64: 185 | F64: Eduardo
A65: 45281 | B65: =A65 -> 45281 | C65: Manhã | D65: Monsenhor Idelfonso | E65: 81 | F65: Milena e Alaide | I65: Total | K65: =SUM(K44:K64) -> 446.25 | N65: Total | P65: =SUM(P44:P64) -> 0
A66: 45282 | B66: =A66 -> 45282 | C66: Manhã | D66: Pe Marcos | E66: 160 | F66: Oscar e Edna
A67: 45283 | B67: =A67 -> 45283 | C67: Noite | D67: Pe Josieldo | E67: 174 | F67: Eduardo e Vieira
A68: 45284 | B68: =A68 -> 45284 | C68: Manhã | D68: Pe Josieldo | E68: 653 | F68: Marcos e William
C69: Noite | D69: Pe Josieldo | E69: 900 | F69: Wandson e Myrtes
A70: 45285 | B70: =A70 -> 45285 | C70: Manhã | D70: Monsenhor Idelfonso | E70: 896 | F70: Ailton e Vieira
A71: 45286 | B71: =A71 -> 45286 | C71: Manhã | D71: Pe Marcos | E71: 45 | F71: Edna e Clediana
A72: 45287 | B72: =A72 -> 45287 | C72: Manhã | D72: Monsenhor Idelfonso | E72: 28 | F72: Ailton e Liliane
A73: 45288 | B73: =A73 -> 45288 | C73: Manhã | D73: Monsenhor Idelfonso | E73: 125 | F73: Wilson e Alaide
A74: 45289 | B74: =A74 -> 45289 | C74: Manhã | D74: Pe Marcos | E74: 110 | F74: Oscar e Neide
A75: 45291 | B75: =A75 -> 45291 | C75: Manhã | E75: 571 | F75: Marcos e William
C76: Noite | E76: 275 | F76: Eduardo e Wandson
A77: Total | E77: =SUM(E44:E76) -> 10392.6
A79: Janeiro/2024
A80: COLETAS | I80: INTENÇÕES | N80: EMPRÉSTIMOS
A81: Data | B81: Dia | C81: Turno | D81: Celebrante | E81: Valor coleta | F81: Responsáveis | G81: Observação | I81: Data | J81: Dia da semana | K81: Valor | L81: Observação | N81: Data | O81: Dia da semana | P81: Valor | Q81: Observação
A82: 45292 | B82: =A82 -> 45292 | C82: Noite | D82: Pe Josieldo | E82: 799 | F82: Ailton e Liliane | I82: 45294 | J82: =I82 -> 45294 | K82: 40.45
A83: 45293 | B83: =A83 -> 45293 | C83: Manhã | D83: Pe Willame | E83: 42 | F83: Vieira e Clediana | I83: 45297 | J83: =I83 -> 45297 | K83: 29
A84: 45294 | B84: =A84 -> 45294 | C84: Manhã | D84: Monsenhor Idlefonso | E84: 53 | F84: Ailton e Edna | I84: 45301 | J84: =I84 -> 45301 | K84: 40.1 | O84: =N84
A85: 45295 | B85: =A85 -> 45295 | C85: Manhã | D85: Monsenhor Idlefonso | E85: 36 | F85: Milena e Alaide | I85: 45308 | J85: =I85 -> 45308 | K85: 97.4
A86: 45296 | B86: =A86 -> 45296 | C86: Manhã | D86: Pe Marcos | E86: 117 | F86: João Paulo e Bernardo | I86: 45315 | J86: =I86 -> 45315 | K86: 58.8 | N86: Total | P86: =SUM(P82:P85) -> 0
C87: Noite | D87: Pe Josieldo | E87: 292 | F87: William e Myrtes | I87: 45322 | J87: =I87 -> 45322 | K87: 102.2
A88: 45298 | B88: =A88 -> 45298 | C88: Manhã | D88: Pe Josieldo | E88: 428 | F88: Wilson Correia
C89: Noite | D89: Pe Watson | E89: 790 | F89: Silvana e Myrthes | N89: DOAÇÃO
A90: 45299 | B90: =A90 -> 45299 | C90: Manhã | D90: Monsenhor Idlefonso | E90: 114 | F90: Bernardo e Ana Lúcia | N90: Data | O90: Dia da semana | P90: Valor | Q90: Observação
A91: 45300 | B91: =A91 -> 45300 | C91: Manhã | D91: Pe Marcos | E91: 65 | F91: Wilson e Clediana | N91: 45293 | O91: =N91 -> 45293 | P91: 200 | Q91: Oscar
A92: 45301 | B92: =A92 -> 45301 | C92: Manhã | D92: Monsenhor Idlefonso | E92: 64 | F92: Liliane e Adaila
A93: 45302 | B93: =A93 -> 45302 | C93: Noite | D93: Monsenhor Idlefonso | E93: 155 | F93: Milena e Alaide
A94: 45303 | B94: =A94 -> 45303 | C94: Manhã | D94: Pe Josieldo | E94: 108 | F94: João Paulo e Edna
A95: 45304 | B95: =A95 -> 45304
A96: 45305 | B96: =A96 -> 45305 | C96: Manhã | D96: Pe Josieldo | E96: 345 | F96: Marcos
A97: 45305 | B97: =A97 -> 45305 | C97: Noite | D97: Pe Paulo Aniceto | E97: 900 | F97: Eduardo e Wandson
A98: 45306 | B98: =A98 -> 45306 | C98: Manhã | D98: Monsenhor Idlefonso | E98: 48 | F98: Bernardo e Ana Lúcia
A99: 45307 | B99: =A99 -> 45307 | C99: Manhã | D99: Pe Marcos | E99: 98 | F99: Ailton e Liliane
A100: 45308 | B100: =A100 -> 45308 | C100: Noite | D100: Monsenhor Idlefonso | E100: 120 | F100: Clediana e Edna
A101: 45309 | B101: =A101 -> 45309 | C101: Manhã | D101: Monsenhor Idlefonso | E101: 98 | F101: Sávio e Albaniza
A102: 45310 | B102: =A102 -> 45310 | C102: Noite | D102: Pe Marcos | E102: 146 | F102: Vieria e João Paulo
A103: 45312 | B103: =A103 -> 45312 | C103: Manhã | D103: Pe Josieldo | E103: 585 | F103: Marcos e William
...

Sheet Despesas
A1: x | B1: Data | C1: Descrição | D1: Qtde | E1: Vlr. Unit | F1: Valor | G1: Valor Doc | H1: Padres | I1: Fornecedor | J1: Observação | K1: Nota | L1: Recibo | M1: Tapete
A2: Novembro/2023
A3: 2023/11 | B3: 45231 | C3: Velas ( Altar, Santíssimo e diárias ) | D3: 4 | E3: 18.9 | F3: 75.6 | G3: 75.6 | H3: FALSE | I3: Renna Luz | J3: Velas 15 x 7 - Coroa do Advento. Recibo 30/10
A4: 2023/11 | B4: 45231 | C4: Carvão Tablete | D4: 3 | E4: 10 | F4: 30 | G4: 30 | H4: FALSE | I4: Casa de Maria | J4: Carvão
A5: 2023/11 | B5: 45233 | C5: Espórtulas | D5: 1 | E5: 150 | F5: 150 | G5: 150 | H5: TRUE | I5: Padre Marcos | J5: Missa manhã
A6: 2023/11 | B6: 45233 | C6: Espórtulas | D6: 1 | E6: 150 | F6: 150 | G6: 150 | H6: TRUE | I6: Padre Josieldo | J6: Missa das Famílias
A7: 2023/11 | B7: 45233 | C7: Velas ( Altar, Santíssimo e diárias ) | D7: 13 | E7: 17.01 | F7: 221.13 | G7: 221.13 | H7: FALSE | I7: Renna Luz | J7: Velas 15 x 7 Brancas
A8: 2023/11 | B8: 45235 | C8: Espórtulas | D8: 1 | E8: 200 | F8: 200 | G8: 200 | H8: TRUE | I8: Padre Josieldo | J8: Missa manhã
A9: 2023/11 | B9: 45235 | C9: Espórtulas | D9: 1 | E9: 200 | F9: 200 | G9: 200 | H9: TRUE | I9: Padre Raphael | J9: Missa noite
A10: 2023/11 | B10: 45236 | C10: Papel toalha | D10: 2 | E10: 6.29 | F10: =D10*E10 -> 12.58 | G10: =SUM(F10:F12) -> 21.46 | H10: FALSE | I10: Center Box
A11: 2023/11 | B11: 45236 | C11: Água Sanitária | D11: 1 | E11: 1.59 | F11: =D11*E11 -> 1.59
A12: 2023/11 | B12: 45236 | C12: Cheirinho ( anti-môfo) | D12: 1 | E12: 7.29 | F12: =D12*E12 -> 7.29
A13: 2023/11 | B13: 45236 | C13: Partículas | D13: 3 | E13: 35 | F13: =D13*E13 -> 105 | G13: =SUM(F13:F15) -> 175 | H13: FALSE | I13: Mosteiro da Imaculada Conceição e São José | J13: hóstias pequenas. Pct com 1k
A14: 2023/11 | B14: 45236 | C14: Partículas | D14: 1 | E14: 35 | F14: =D14*E14 -> 35 | J14: Hóstias 10 cm. pct com 10 und
A15: 2023/11 | B15: 45236 | C15: Partículas | D15: 1 | E15: 35 | F15: =D15*E15 -> 35 | J15: Hóstias 14 cm. pct com 10 und
A16: 2023/11 | B16: 45236 | C16: Água | D16: 1 | E16: 12 | F16: 12 | G16: 12 | H16: FALSE | I16: Posto Caribe | J16: Garrafão 20 lts indaiá
A17: 2023/11 | B17: 45237 | C17: Espórtulas | D17: 1 | E17: 150 | F17: 150 | G17: 150 | H17: TRUE | I17: Padre Marcos | J17: Missa 07/11 - manhã
A18: 2023/11 | B18: 45237 | C18: Alcóol | D18: 2 | E18: 8.69 | F18: =E18*D18 -> 17.38 | G18: =F18 -> 17.38 | H18: FALSE | I18: Frangolândia | J18: Alcóol
A19: 2023/11 | B19: 45238 | C19: Devolução de Empréstimos | D19: 1 | E19: 700 | F19: 700 | G19: 700 | H19: FALSE | J19: Valor usado para pgto de espórtulas dos dias 3 e 5
A20: 2023/11 | B20: 45240 | C20: Espórtulas | D20: 1 | E20: 150 | F20: 150 | G20: 150 | H20: TRUE | I20: Padre Josieldo | J20: Missa sexta - 10/11 - manhã
A21: 2023/11 | B21: 45240 | C21: Velas ( Altar, Santíssimo e diárias ) | D21: 3 | E21: 7.7 | F21: =D21*E21 -> 23.1 | G21: 23.1 | H21: FALSE | I21: Renna Luz | J21: Velas cast lisa (par)
A22: 2023/11 | B22: 45240 | C22: Lavanderia | D22: 1 | E22: 116 | F22: =D22*E22 -> 116 | G22: 116 | H22: FALSE | I22: Lavanderia Lig-Lave | J22: Túnicas dos padres
A23: 2023/11 | B23: 45241 | C23: Outros | D23: 1 | E23: 80 | F23: 80 | G23: 80 | H23: FALSE | I23: Chaveiro | J23: Fechadura armário sacristia
A24: 2023/11 | B24: 45242 | C24: Espórtulas | D24: 1 | E24: 200 | F24: 200 | G24: 200 | H24: TRUE | I24: Padre Josieldo | J24: Missa domingo 10/11 - manhã
A25: 2023/11 | B25: 45242 | C25: Espórtulas | D25: 1 | E25: 200 | F25: 200 | G25: 200 | H25: TRUE | I25: Padre Watson | J25: Missa domingo 10/11 - noite
A26: 2023/11 | B26: 45244 | C26: Espórtulas | D26: 1 | E26: 150 | F26: 150 | G26: 150 | H26: TRUE | I26: Padre Marcos | J26: Missa terça-feira 14/11 manhã
A27: 2023/11 | B27: 45244 | C27: Produtos de limpeza | D27: 1 | E27: 48.1 | F27: 48.1 | G27: 48.1 | H27: FALSE | I27: Distrilimp ind. com... | J27: Limpeza do banheiro da sacristia
A28: 2023/11 | B28: 45245 | C28: Descartáveis (Copos, pratos) | D28: 4 | E28: 2.19 | F28: =D28*E28 -> 8.76 | G28: =SUM(F28:F38) -> 125.94 | H28: FALSE | I28: Centerbox | J28: Partos descartáveis
A29: 2023/11 | B29: 45245 | C29: Fraternidade | Aniversariantes | D29: 2 | E29: 2.29 | F29: =D29*E29 -> 4.58 | J29: Guardanapos
A30: 2023/11 | B30: 45245 | C30: Fraternidade | Aniversariantes | D30: 1 | E30: 1.39 | F30: =D30*E30 -> 1.39 | J30: Palitos de dente
A31: 2023/11 | B31: 45245 | C31: Fraternidade | Aniversariantes | D31: 1 | E31: 5.99 | F31: =D31*E31 -> 5.99 | J31: Vela vulcão
A32: 2023/11 | B32: 45245 | C32: Produtos de limpeza | D32: 1 | E32: 5.99 | F32: =D32*E32 -> 5.99 | J32: Multiuso Veja
A33: 2023/11 | B33: 45245 | C33: Produtos de limpeza | D33: 1 | E33: 5.99 | F33: =D33*E33 -> 5.99 | J33: Lustra móveis
A34: 2023/11 | B34: 45245 | C34: Produtos de limpeza | D34: 1 | E34: 7.99 | F34: =D34*E34 -> 7.99 | J34: Esponja
A35: 2023/11 | B35: 45245 | C35: Produtos de limpeza | D35: 1 | E35: 2.39 | F35: =D35*E35 -> 2.39 | J35: Detergente líquido
A36: 2023/11 | B36: 45245 | C36: Produtos de limpeza | D36: 1 | E36: 13.99 | F36: =D36*E36 -> 13.99 | J36: Desinfetante kalipto
A37: 2023/11 | B37: 45245 | C37: Produtos de limpeza | D37: 2 | E37: 4.44 | F37: =D37*E37 -> 8.88 | J37: Pedra sanitário
A38: 2023/11 | B38: 45245 | C38: Produtos de limpeza | D38: 1 | E38: 59.99 | F38: =D38*E38 -> 59.99 | J38: Polidor silvo 2ooml
A39: 2023/11 | B39: 45247 | C39: Espórtulas | D39: 1 | E39: 150 | F39: 150 | G39: 150 | H39: TRUE | I39: Padre Josieldo | J39: Missa sexta-feira 17/11 - manhã
A40: 2023/11 | B40: 45249 | C40: Espórtulas | D40: 1 | E40: 200 | F40: 200 | G40: 200 | H40: TRUE | I40: Padre Josieldo | J40: Missa domingo 19/11 - manhã
A41: 2023/11 | B41: 45249 | C41: Espórtulas | D41: 1 | E41: 200 | F41: 200 | G41: 200 | H41: TRUE | I41: Padre Paulo Aniceto | J41: Missa domingo 19/11 - noite
A42: 2023/11 | B42: 45250 | C42: Lavanderia | D42: 1 | E42: 115.43 | F42: =D42*E42 -> 115.43 | G42: 115.43 | H42: FALSE | I42: Clean&Soft Lavanderia | J42: Toalhas diversas
A43: 2023/11 | B43: 45251 | C43: Lavanderia | D43: 1 | E43: 155.8 | F43: 155.8 | G43: 155.8 | H43: FALSE | I43: Clean&Soft Lavanderia | J43: 4 Casulas | 3-Estolas | 1-Batina | 1 manta altar | 1-toalha credença
A44: 2023/11 | B44: 45253 | C44: Livro Diretório | D44: 1 | E44: 42.5 | F44: 42.5 | G44: 42.5 | H44: FALSE | I44: Edições Paulinas | J44: Livro diretório
A45: 2023/11 | B45: 45253 | C45: Partículas | D45: 1 | E45: 70 | F45: 70 | G45: 70 | H45: FALSE | I45: Mosteiro Imaculada Conceição | J45: Partículas assembléia
A46: 2023/11 | B46: 45253 | C46: Material administrativo | D46: 3 | E46: 2.5 | F46: =D46*E46 -> 7.5 | G46: 12.5 | H46: FALSE | I46: Danart | J46: 3 pastas colecioandora pequenas
A47: 2023/11 | B47: 45253 | C47: Material administrativo | D47: 1 | E47: 5 | F47: 5 | J47: 1 clipes cx com 100
A48: 2023/11 | B48: 45254 | C48: Decoração Capela | D48: 1 | E48: 95 | F48: 95 | G48: 95 | H48: FALSE | I48: Kato Flores | J48: Rosas para capela missa Célia Nóbrega | Cristo Rei
A49: 2023/11 | B49: 45254 | C49: Espórtulas | D49: 1 | E49: 150 | F49: 150 | G49: 150 | H49: TRUE | I49: Padre Marcos | J49: Missa sexta-feira 24-11 manhã
A50: 2023/11 | B50: 45256 | C50: Espórtulas | D50: 1 | E50: 200 | F50: 200 | G50: 200 | H50: TRUE | I50: Padre Josieldo | J50: Missa domingo 26/11 - manhã
A51: 2023/11 | B51: 45256 | C51: Espórtulas | D51: 22 | E51: 130 | F51: =E51*D51 -> 2860 | G51: 2860 | H51: TRUE | I51: Monsenhor Idelfonso | J51: Missas/Confissões do mês de novembro
A52: 2023/11 | B52: 45259 | C52: Decoração Capela | D52: 1 | E52: 24.9 | F52: 24.9 | G52: 24.9 | H52: FALSE | I52: Normatel | J52: Tinta spray metálico ouro
A53: 2023/11 | B53: 45260 | C53: Repasse AFC | D53: 1 | E53: 4000 | F53: 4000 | G53: 4000 | I53: Financeiro FACE | J53: Repasse de saldo da coleta das missas
A54: Totais | F54: =SUM(F3:F53) -> 11471.84 | G54: =SUM(G3:G53) -> 11471.84
A55: Dezembro/2023
A56: 2023/12 | B56: 45261 | C56: Espórtulas | D56: 1 | E56: 150 | F56: 150 | G56: 150 | H56: TRUE | I56: Padre Marcos | J56: Missa sexta-feira 01-12 manhã
A57: 2023/12 | B57: 45261 | C57: Lavanderia | D57: 1 | E57: 220 | F57: 220 | G57: 220 | H57: FALSE | I57: Clean&Soft Lavanderia | J57: 20 batas leitores
A58: 2023/12 | B58: 45261 | C58: Água | D58: 2 | E58: 12 | F58: =D58*E58 -> 24 | G58: =F58 -> 24 | H58: FALSE | I58: Posto Caribe | J58: 2 Águas indaiá
A59: 2023/12 | B59: 45262 | C59: Espórtulas | D59: 1 | E59: 150 | F59: 150 | G59: 150 | H59: TRUE | I59: Padre Raphael | J59: Missa sábado 02-12 retiro juventude
A60: 2023/12 | B60: 45263 | C60: Espórtulas | D60: 1 | E60: 200 | F60: 200 | G60: 200 | H60: TRUE | I60: Padre Edvânio | J60: Missa domingo 03-12 manhã
A61: 2023/12 | B61: 45265 | C61: Espórtulas | D61: 1 | E61: 150 | F61: 150 | G61: 150 | H61: TRUE | I61: Padre Marcos | J61: Missa terça-feira 05-12 manhã
A62: 2023/12 | B62: 45265 | C62: Papel toalha | D62: 1 | E62: 13.44 | F62: =D62*E62 -> 13.44 | G62: =SUM(F62:F65) -> 52.51 | H62: FALSE | I62: Centerbox | J62: papel higiênico
A63: 2023/12 | B63: 45265 | C63: Alcóol | D63: 1 | E63: 11.59 | F63: =D63*E63 -> 11.59 | J63: alcóol
A64: 2023/12 | B64: 45265 | C64: Pilha | D64: 1 | E64: 19.99 | F64: =D64*E64 -> 19.99 | J64: pilha palito
A65: 2023/12 | B65: 45265 | C65: Produtos de limpeza | D65: 1 | E65: 7.49 | F65: =D65*E65 -> 7.49 | J65: papel higiênico
A66: 2023/12 | B66: 45265 | C66: Partículas | D66: 1 | E66: 24 | F66: 24 | G66: 24 | H66: FALSE | I66: Paulinas | J66: Partículas 12 cm sacerdote
A67: 2023/12 | B67: 45265 | C67: Partículas | D67: 1 | E67: 70 | F67: 70 | G67: 70 | H67: FALSE | I67: Mosteiro Imaculada Conceição | J67: Partículas assembléia
H68: FALSE
A69: 2023/12 | B69: 45266 | C69: Papel toalha | D69: 1 | E69: 6.29 | F69: 6.29 | G69: 10.64 | H69: FALSE | I69: Centrebox | J69: papel toalha
A70: 2023/12 | B70: 45266 | C70: Acessórios sacristia | D70: 1 | E70: 17.79 | F70: =17.79-13.44 -> 4.35 | J70: pote para armazenar partículas sacerdote
A71: 2023/12 | B71: 45270 | C71: Espórtulas | D71: 1 | E71: 200 | F71: 200 | G71: 200 | H71: TRUE | I71: Padre Diogo Félix | J71: Missa domingo 10-12 manhã
A72: 2023/12 | B72: 45270 | C72: Espórtulas | D72: 1 | E72: 200 | F72: 200 | G72: 200 | H72: TRUE | I72: Padre Watson | J72: Missa domingo 10-12 noite
A73: 2023/12 | B73: 45272 | C73: Espórtulas | D73: 1 | E73: 150 | F73: 150 | G73: 150 | H73: TRUE | I73: Padre Marcos | J73: Missa terça-feira 12-12 manhã
A74: 2023/12 | B74: 45273 | C74: Espórtulas | D74: 1 | E74: 150 | F74: 150 | G74: 150 | H74: TRUE | I74: Padre Neto | J74: Missa natal face quarta-feira 13-12 noite
A75: 2023/12 | B75: 45273 | C75: Decoração Capela | D75: 1 | E75: 68.4 | F75: 68.4 | G75: 68.4 | H75: FALSE | I75: Kato Flores | J75: Rosas para o altar - missa de natal - 13/12
A76: 2023/12 | B76: 45275 | C76: Espórtulas | D76: 1 | E76: 150 | F76: 150 | G76: 150 | H76: TRUE | I76: Padre Josieldo | J76: Missa sexta-feira 15-12 manhã
A77: 2023/12 | B77: 45277 | C77: Espórtulas | D77: 1 | E77: 200 | F77: 200 | G77: 200 | H77: TRUE | I77: Padre Josieldo | J77: Missa domingo 17-12 manhã
A78: 2023/12 | B78: 45277 | C78: Espórtulas | D78: 1 | E78: 200 | F78: 200 | G78: 200 | H78: TRUE | I78: Frei Ricardo Régis | J78: Missa domingo 17-12 manhã
A79: 2023/12 | B79: 45277 | C79: Produtos de limpeza | D79: 1 | E79: 21.38 | F79: 21.38 | G79: 21.38 | H79: FALSE | I79: Frangolândia | J79: produtos de limpeza
A80: 2023/12 | B80: 45278 | C80: Repasse Paróquia São Vicente | D80: 1 | E80: 625 | F80: 625 | G80: 625 | H80: FALSE | J80: Repasse paróquia São Vicente
A81: 2023/12 | B81: 45278 | C81: Lavanderia | D81: 1 | E81: 45.2 | F81: 45.2 | G81: 45.2 | H81: FALSE | I81: Clean&Soft Lavanderia | J81: 1 toalha | 1 passadeira | 1 pano de bandeja
A82: 2023/12 | B82: 45278 | C82: Partículas | D82: 1 | E82: 175 | F82: 175 | G82: 175 | H82: FALSE | I82: Mosteiro Imaculada Conceição | J82: Partículas assembléia | magnas
A83: 2023/12 | B83: 45278 | C83: Velas ( Altar, Santíssimo e diárias ) | D83: 1 | E83: 98.7 | F83: 98.7 | G83: 98.7 | H83: FALSE | I83: Rena Comercial | J83: 3 pct de velas | 3 velas c7x15
A84: 2023/12 | B84: 45279 | C84: Espórtulas | D84: 1 | E84: 150 | F84: 150 | G84: 150 | H84: TRUE | I84: Padre Marcos | J84: Missa terça-feira 19-12 manhã
A85: 2023/12 | B85: 45281 | C85: Acessórios sacristia | D85: 2 | E85: 20.5 | F85: 41 | G85: 41 | H85: FALSE | I85: Jocelia Guedes | J85: 2 eletroduto roscavel
A86: 2023/12 | B86: 45281 | C86: Acessórios sacristia | D86: 1 | E86: 48 | F86: 48 | G86: 48 | H86: FALSE | I86: Supplex | J86: Fita dupla face
A87: 2023/12 | B87: 45281 | C87: Espórtulas | D87: 1 | E87: 3020 | F87: 3020 | G87: 3020 | H87: TRUE | I87: Monsenho Idelfonso | J87: Missas do mês de dezembro
A88: 2023/12 | B88: 45282 | C88: Produtos de limpeza | D88: 1 | E88: 68.87 | F88: 68.87 | G88: 68.87 | H88: FALSE | I88: Frangolândia | J88: produtos de limpeza
A89: 2023/12 | B89: 45282 | C89: Espórtulas | D89: 1 | E89: 150 | F89: 150 | G89: 150 | H89: TRUE | I89: Padre Marcos | J89: Missa sexta-feira 22-12 manhã
A90: 2023/12 | B90: 45283 | C90: Espórtulas | D90: 1 | E90: 200 | F90: 200 | G90: 200 | H90: TRUE | I90: Padre Josieldo | J90: Missa sábado 23-12 noite (4o domingo advento)
A91: 2023/12 | B91: 45284 | C91: Espórtulas | D91: 1 | E91: 200 | F91: 200 | G91: 200 | H91: TRUE | I91: Padre Josieldo | J91: Missa domingo 24-12 manhã (4o domingo advento)
A92: 2023/12 | B92: 45284 | C92: Espórtulas | D92: 1 | E92: 200 | F92: 200 | G92: 200 | H92: TRUE | I92: Padre Josieldo | J92: Missa domingo 24-12 noite ( missa virgilia do natal)
... A97: 2023/12 | B97: 45286 | C97: Lavanderia | D97: 1 | E97: 192.67 | F97: 192.67 | G97: 192.67 | H97: FALSE | I97: Clean&Soft Lavanderia | J97: 1 casula | 1 Batina | 1 Passadeira | 1 estola | 1 toalha rosto | pano de chão | 3 Toalhas | 1 Toalha ambão | 1 Protetor altar | 1 pano de chão | 1 pacjo copa
A98: 45261 | B98: 45287 | C98: Repasse AFC | D98: 1 | E98: 1000 | F98: 1000 | G98: 1000 | H98: FALSE | I98: Financeiro FACE | J98: Repasse de saldo da coleta das missas
A99: 2023/12 | B99: 45289 | C99: Espórtulas | D99: 1 | E99: 150 | F99: 150 | G99: 150 | H99: TRUE | I99: Padre Marcos | J99: Missa sexta 29-12 noite
A100: 2023/12 | B100: 45291 | C100: Espórtulas | D100: 1 | E100: 200 | F100: 200 | G100: 200 | H100: TRUE | I100: Padre João Paulo | J100: Missa domingo 31-12 manhã
A101: 2023/12 | B101: 45291 | C101: Espórtulas | D101: 1 | E101: 200 | F101: 200 | G101: 200 | H101: TRUE | I101: Padre Josieldo | J101: Missa domingo 31-12 noite
A102: 2023/12 | B102: 45291 | C102: Outros | D102: 1 | E102: 50 | F102: 50 | G102: 50 | H102: FALSE | J102: Transporte solicitado pelo sacerdote
H103: FALSE
A104: Totais | F104: =SUM(F56:F103) -> 9674.37 | G104: =SUM(G56:G103) -> 9674.37
...

Sheet Sacerdotes
A1: Dia | B1: Dia da semana | C1: Turno | D1: Sacerdote | E1: Descrição | F1: Valor | G1: Observação | H1: Pago
A2: Novembro/2023
A3: 45231 | B3: =A3 -> 45231 | C3: Manhã | D3: Idelfonso | E3: Missa | F3: 130 | H3: TRUE
A4: 45232 | B4: =A4 -> 45232 | C4: Manhã | D4: Idelfonso | E4: Missa | F4: 130 | H4: TRUE
A5: 45233 | B5: =A5 -> 45233 | C5: Manhã | D5: Marcos | E5: Missa | F5: 150 | H5: TRUE
D6: Idelfonso | E6: Missa | F6: 130 | H6: TRUE | K6: Resumo do mês NOV/2023 - Espórtulas
C7: Noite | D7: Josieldo | E7: Missa | F7: 150 | G7: Missa das famílias | H7: TRUE | K7: Sacerdote | L7: Missa | M7: Confissão | N7: Total | O7: Total Previsto | P7: Total Realizado | Q7: Saldo a Pagar
A8: 45235 | B8: =A8 -> 45235 | C8: Manhã | D8: Josieldo | E8: Missa | F8: 200 | H8: TRUE | K8: Josieldo | L8: =COUNTIFS($D$3:$D$42, $K8,$E$3:$E$42,$L$7) -> 7 | M8: =COUNTIFS($D$3:$D$42, $K8,$E$3:$E$42,$M$7) -> 0 | N8: =L8+M8 -> 7 | O8: =SUMIFS($F$3:$F$42,$D$3:$D$42,$K8) -> 1250 | P8: =SUMIFS($F$3:$F$42,$D$3:$D$42,$K8,$H$3:$H$42,TRUE) -> 1250 | Q8: =O8-P8 -> 0
C9: Noite | D9: Raphael | E9: Missa | F9: 200 | H9: TRUE | K9: Marcos | L9: =COUNTIFS($D$3:$D$42, $K9,$E$3:$E$42,$L$7) -> 6 | M9: =COUNTIFS($D$3:$D$42, $K9,$E$3:$E$42,$M$7) -> 0 | N9: =L9+M9 -> 6 | O9: =SUMIFS($F$3:$F$42,$D$3:$D$42,$K9) -> 600 | P9: =SUMIFS($F$3:$F$42,$D$3:$D$42,$K9,$H$3:$H$42,TRUE) -> 600 | Q9: =O9-P9 -> 0
A10: 45236 | B10: =A10 -> 45236 | C10: Manhã | D10: Idelfonso | E10: Missa | F10: 130 | H10: TRUE | K10: Idelfonso | L10: =COUNTIFS($D$3:$D$42, $K10,$E$3:$E$42,$L$7) -> 15 | M10: =COUNTIFS($D$3:$D$42, $K10,$E$3:$E$42,$M$7) -> 6 | N10: =L10+M10 -> 21 | O10: =SUMIFS($F$3:$F$42,$D$3:$D$42,$K10) -> 2730 | P10: =SUMIFS($F$3:$F$42,$D$3:$D$42,$K10,$H$3:$H$42,TRUE) -> 2730 | Q10: =O10-P10 -> 0
A11: 45237 | B11: =A11 -> 45237 | C11: Manhã | D11: Marcos | E11: Missa | F11: 150 | H11: TRUE | K11: Raphael | L11: =COUNTIFS($D$3:$D$42, $K11,$E$3:$E$42,$L$7) -> 1 | M11: =COUNTIFS($D$3:$D$42, $K11,$E$3:$E$42,$M$7) -> 0 | N11: =L11+M11 -> 1 | O11: =SUMIFS($F$3:$F$42,$D$3:$D$42,$K11) -> 200 | P11: =SUMIFS($F$3:$F$42,$D$3:$D$42,$K11,$H$3:$H$42,TRUE) -> 200 | Q11: =O11-P11 -> 0
C12: Manhã | D12: Idelfonso | E12: Confissão | F12: 130 | H12: TRUE | K12: Watson | L12: =COUNTIFS($D$3:$D$42, $K12,$E$3:$E$42,$L$7) -> 1 | M12: =COUNTIFS($D$3:$D$42, $K12,$E$3:$E$42,$M$7) -> 0 | N12: =L12+M12 -> 1 | O12: =SUMIFS($F$3:$F$42,$D$3:$D$42,$K12) -> 200 | P12: =SUMIFS($F$3:$F$42,$D$3:$D$42,$K12,$H$3:$H$42,TRUE) -> 200 | Q12: =O12-P12 -> 0
A13: 45238 | B13: =A13 -> 45238 | C13: Manhã | D13: Idelfonso | E13: Missa | F13: 130 | H13: TRUE | K13: Paulo Aniceto | L13: =COUNTIFS($D$3:$D$42, $K13,$E$3:$E$42,$L$7) -> 1 | M13: =COUNTIFS($D$3:$D$42, $K13,$E$3:$E$42,$M$7) -> 0 | N13: =L13+M13 -> 1 | O13: =SUMIFS($F$3:$F$42,$D$3:$D$42,$K13) -> 200 | P13: =SUMIFS($F$3:$F$42,$D$3:$D$42,$K13,$H$3:$H$42,TRUE) -> 200 | Q13: =O13-P13 -> 0
A14: 45239 | B14: =A14 -> 45239 | C14: Manhã | D14: Idelfonso | E14: Missa | F14: 130 | H14: TRUE | K14: Diego Juaçaba | L14: =COUNTIFS($D$3:$D$42, $K14,$E$3:$E$42,$L$7) -> 3 | M14: =COUNTIFS($D$3:$D$42, $K14,$E$3:$E$42,$M$7) -> 0 | N14: =L14+M14 -> 3 | O14: =SUMIFS($F$3:$F$42,$D$3:$D$42,$K14) -> 130 | P14: =SUMIFS($F$3:$F$42,$D$3:$D$42,$K14,$H$3:$H$42,TRUE) -> 130 | Q14: =O14-P14 -> 0
A15: 45240 | B15: =A15 -> 45240 | C15: Manhã | D15: Josieldo | E15: Missa | F15: 150 | H15: TRUE
D16: Idelfonso | E16: Confissão | F16: 130 | H16: TRUE
A17: 45242 | B17: =A17 -> 45242 | C17: Manhã | D17: Josieldo | E17: Missa | F17: 200 | H17: TRUE
C18: Noite | D18: Watson | E18: Missa | F18: 200 | H18: TRUE
A19: 45243 | B19: =A19 -> 45243 | C19: Manhã | D19: Idelfonso | E19: Missa | F19: 130 | H19: TRUE
A20: 45244 | B20: =A20 -> 45244 | C20: Manhã | D20: Marcos | E20: Missa | F20: 150 | H20: TRUE
D21: Idelfonso | E21: Confissão | F21: 130 | H21: TRUE
A22: 45245 | B22: =A22 -> 45245 | C22: Manhã | D22: Idelfonso | E22: Missa | F22: 130 | H22: TRUE
A23: 45246 | B23: =A23 -> 45246 | C23: Manhã | D23: Idelfonso | E23: Missa | F23: 130 | H23: TRUE | K23: Total | L23: =SUM(L8:L22) -> 34 | M23: =SUM(M8:M22) -> 6 | N23: =SUM(N8:N22) -> 40 | O23: =SUM(O8:O22) -> 5310 | P23: =SUM(P8:P22) -> 5310 | Q23: =SUM(Q8:Q22) -> 0
A24: 45247 | B24: =A24 -> 45247 | C24: Manhã | D24: Josieldo | E24: Missa | F24: 150 | H24: TRUE
C25: Manhã | D25: Idelfonso | E25: Confissão | F25: 130 | H25: TRUE
A26: 45249 | B26: =A26 -> 45249 | C26: Manhã | D26: Josieldo | E26: Missa | F26: 200 | H26: TRUE
C27: Noite | D27: Paulo Aniceto | E27: Missa | F27: 200 | H27: TRUE
A28: 45250 | B28: =A28 -> 45250 | C28: Manhã | D28: Idelfonso | E28: Missa | F28: 130 | H28: TRUE
A29: 45251 | B29: =A29 -> 45251 | C29: Manhã | D29: Marcos | E29: Missa | F29: 0 | G29: Pe Marcos não pôde celebrar | H29: FALSE
D30: Idelfonso | E30: Missa | F30: 130 | H30: TRUE
A31: 45252 | B31: =A31 -> 45252 | C31: Manhã | D31: Idelfonso | E31: Missa | F31: 130 | H31: TRUE
A32: 45253 | B32: =A32 -> 45253 | C32: Manhã | D32: Idelfonso | E32: Missa | F32: 130 | H32: TRUE
A33: 45254 | B33: =A33 -> 45254 | C33: Manhã | D33: Marcos | E33: Missa | F33: 150 | H33: TRUE
D34: Idelfonso | E34: Confissão | F34: 130 | H34: TRUE
A35: 45256 | B35: =A35 -> 45256 | C35: Manhã | D35: Josieldo | E35: Missa | F35: 200 | H35: TRUE
C36: Noite | D36: Diego Juaçaba | E36: Missa | F36: 0 | G36: Não aceitou a espórtula | H36: FALSE
A37: 45257 | B37: =A37 -> 45257 | C37: Manhã | D37: Idelfonso | E37: Missa | F37: 130 | H37: TRUE
A38: 45258 | B38: =A38 -> 45258 | C38: Manhã | D38: Marcos | E38: Missa | F38: 0 | G38: Pe Marcos não pôde celebrar | H38: FALSE
D39: Idelfonso | E39: Missa | F39: 130 | H39: TRUE
A40: 45259 | B40: =A40 -> 45259 | C40: Manhã | D40: Diego Juaçaba | E40: Missa | F40: 0 | G40: Não aceitou a espórtula | H40: FALSE
C41: Manhã | D41: Idelfonso | E41: Confissão | F41: 130 | H41: TRUE
A42: 45260 | B42: =A42 -> 45260 | C42: Manhã | D42: Diego Juaçaba | E42: Missa | F42: 130 | H42: TRUE
A43: Total | F43: =SUM(F3:F42) -> 5310
A44: Dezembro/2023
A45: 45261 | B45: =A45 -> 45261 | C45: Manhã | D45: Marcos | E45: Missa | F45: 150 | H45: TRUE
C46: Manhã | D46: Idelfonso | E46: Confissão | F46: 130 | H46: TRUE
A47: 2 | B47: sábado | C47: Manhã | D47: Raphael | E47: Missa | F47: 150 | G47: Missa retiro dos jovens | H47: TRUE
A48: 45263 | B48: =A48 -> 45263 | C48: Manhã | D48: Edvânio | E48: Missa | F48: 200 | H48: TRUE | K48: Resumo do mês Dez/2023 - Espórtulas
C49: Noite | D49: Idelfonso | E49: Missa | F49: 200 | H49: TRUE | K49: Sacerdote | L49: Missa | M49: Confissão | N49: Total | O49: Total Previsto | P49: Total Realizado | Q49: Saldo a Pagar
A50: 45264 | B50: =A50 -> 45264 | C50: Manhã | D50: Idelfonso | E50: Missa | F50: 130 | H50: TRUE | K50: Josieldo | L50: =COUNTIFS($D$45:$D$87, $K50,$E$45:$E$87,$L$49) -> 5 | M50: =COUNTIFS($D$45:$D$87, $K50,$E$45:$E$87,$M$49) -> 0 | N50: =L50+M50 -> 5 | O50: =SUMIFS($F$45:$F$87,$D$45:$D$87,$K50) -> 1000 | P50: =SUMIFS($F$45:$F$87,$D$45:$D$87,$K50,$H$45:$H$87,TRUE) -> 1000 | Q50: =O50-P50 -> 0
A51: 45265 | B51: =A51 -> 45265 | C51: Manhã | D51: Marcos | E51: Missa | F51: 150 | H51: TRUE | K51: Marcos | L51: =COUNTIFS($D$45:$D$87, $K51,$E$45:$E$87,$L$49) -> 9 | M51: =COUNTIFS($D$45:$D$87, $K51,$E$45:$E$87,$M$49) -> 0 | N51: =L51+M51 -> 9 | O51: =SUMIFS($F$45:$F$87,$D$45:$D$87,$K51) -> 1200 | P51: =SUMIFS($F$45:$F$87,$D$45:$D$87,$K51,$H$45:$H$87,TRUE) -> 1200 | Q51: =O51-P51 -> 0
C52: Manhã | D52: Idelfonso | E52: Confissão | F52: 130 | H52: TRUE | K52: Idelfonso | L52: =COUNTIFS($D$45:$D$87, $K52,$E$45:$E$87,$L$49) -> 13 | M52: =COUNTIFS($D$45:$D$87, $K52,$E$45:$E$87,$M$49) -> 8 | N52: =L52+M52 -> 21 | O52: =SUMIFS($F$45:$F$87,$D$45:$D$87,$K52) -> 2820 | P52: =SUMIFS($F$45:$F$87,$D$45:$D$87,$K52,$H$45:$H$87,TRUE) -> 2820 | Q52: =O52-P52 -> 0
A53: 45266 | B53: =A53 -> 45266 | C53: Manhã | D53: Idelfonso | E53: Missa | F53: 150 | H53: TRUE | K53: Raphael | L53: =COUNTIFS($D$45:$D$87, $K53,$E$45:$E$87,$L$49) -> 1 | M53: =COUNTIFS($D$45:$D$87, $K53,$E$45:$E$87,$M$49) -> 0 | N53: =L53+M53 -> 1 | O53: =SUMIFS($F$45:$F$87,$D$45:$D$87,$K53) -> 150 | P53: =SUMIFS($F$45:$F$87,$D$45:$D$87,$K53,$H$45:$H$87,TRUE) -> 150 | Q53: =O53-P53 -> 0
A54: 45267 | B54: =A54 -> 45267 | C54: Manhã | D54: Idelfonso | E54: Missa | F54: 130 | H54: TRUE | K54: Watson | L54: =COUNTIFS($D$45:$D$87, $K54,$E$45:$E$87,$L$49) -> 1 | M54: =COUNTIFS($D$45:$D$87, $K54,$E$45:$E$87,$M$49) -> 0 | N54: =L54+M54 -> 1 | O54: =SUMIFS($F$45:$F$87,$D$45:$D$87,$K54) -> 200 | P54: =SUMIFS($F$45:$F$87,$D$45:$D$87,$K54,$H$45:$H$87,TRUE) -> 200 | Q54: =O54-P54 -> 0
A55: 45268 | B55: =A55 -> 45268 | C55: Manhã | D55: Marcos | E55: Missa | F55: 0 | G55: Não celebrou | H55: TRUE | K55: Paulo Aniceto | L55: =COUNTIFS($D$45:$D$87, $K55,$E$45:$E$87,$L$49) -> 0 | M55: =COUNTIFS($D$45:$D$87, $K55,$E$45:$E$87,$M$49) -> 0 | N55: =L55+M55 -> 0 | O55: =SUMIFS($F$45:$F$87,$D$45:$D$87,$K55) -> 0 | P55: =SUMIFS($F$45:$F$87,$D$45:$D$87,$K55,$H$45:$H$87,TRUE) -> 0 | Q55: =O55-P55 -> 0
C56: Manhã | D56: Idelfonso | E56: Missa | F56: 130 | H56: TRUE | K56: Diego Juaçaba | L56: =COUNTIFS($D$45:$D$87, $K56,$E$45:$E$87,$L$49) -> 0 | M56: =COUNTIFS($D$45:$D$87, $K56,$E$45:$E$87,$M$49) -> 0 | N56: =L56+M56 -> 0 | O56: =SUMIFS($F$45:$F$87,$D$45:$D$87,$K56) -> 0 | P56: =SUMIFS($F$45:$F$87,$D$45:$D$87,$K56,$H$45:$H$87,TRUE) -> 0 | Q56: =O56-P56 -> 0
A57: 45270 | B57: =A57 -> 45270 | C57: Manhã | D57: Diego Félix | E57: Missa | F57: 200 | H57: TRUE | K57: Diego Félix | L57: =COUNTIFS($D$45:$D$87, $K57,$E$45:$E$87,$L$49) -> 1 | M57: =COUNTIFS($D$45:$D$87, $K57,$E$45:$E$87,$M$49) -> 0 | N57: =L57+M57 -> 1 | O57: =SUMIFS($F$45:$F$87,$D$45:$D$87,$K57) -> 200 | P57: =SUMIFS($F$45:$F$87,$D$45:$D$87,$K57,$H$45:$H$87,TRUE) -> 200 | Q57: =O57-P57 -> 0
C58: Noite | D58: Watson | E58: Missa | F58: 200 | H58: TRUE | K58: Ricardo Régis | L58: =COUNTIFS($D$45:$D$87, $K58,$E$45:$E$87,$L$49) -> 1 | M58: =COUNTIFS($D$45:$D$87, $K58,$E$45:$E$87,$M$49) -> 0 | N58: =L58+M58 -> 1 | O58: =SUMIFS($F$45:$F$87,$D$45:$D$87,$K58) -> 200 | P58: =SUMIFS($F$45:$F$87,$D$45:$D$87,$K58,$H$45:$H$87,TRUE) -> 200 | Q58: =O58-P58 -> 0
A59: 45271 | B59: =A59 -> 45271 | C59: Manhã | D59: Idelfonso | E59: Missa | F59: 130 | H59: TRUE | K59: Edvânio | L59: =COUNTIFS($D$45:$D$87, $K59,$E$45:$E$87,$L$49) -> 2 | M59: =COUNTIFS($D$45:$D$87, $K59,$E$45:$E$87,$M$49) -> 0 | N59: =L59+M59 -> 2 | O59: =SUMIFS($F$45:$F$87,$D$45:$D$87,$K59) -> 400 | P59: =SUMIFS($F$45:$F$87,$D$45:$D$87,$K59,$H$45:$H$87,TRUE) -> 400 | Q59: =O59-P59 -> 0
A60: 45272 | B60: =A60 -> 45272 | C60: Manhã | D60: Marcos | E60: Missa | F60: 150 | H60: TRUE | K60: Neto | L60: =COUNTIFS($D$45:$D$87, $K60,$E$45:$E$87,$L$49) -> 1 | M60: =COUNTIFS($D$45:$D$87, $K60,$E$45:$E$87,$M$49) -> 0 | N60: =L60+M60 -> 1 | O60: =SUMIFS($F$45:$F$87,$D$45:$D$87,$K60) -> 150 | P60: =SUMIFS($F$45:$F$87,$D$45:$D$87,$K60,$H$45:$H$87,TRUE) -> 150 | Q60: =O60-P60 -> 0
C61: Manhã | D61: Idelfonso | E61: Confissão | F61: 130 | H61: TRUE | K61: João Paulo | L61: =COUNTIFS($D$45:$D$87, $K61,$E$45:$E$87,$L$49) -> 1 | M61: =COUNTIFS($D$45:$D$87, $K61,$E$45:$E$87,$M$49) -> 0 | N61: =L61+M61 -> 1 | O61: =SUMIFS($F$45:$F$87,$D$45:$D$87,$K61) -> 200 | P61: =SUMIFS($F$45:$F$87,$D$45:$D$87,$K61,$H$45:$H$87,TRUE) -> 200 | Q61: =O61-P61 -> 0
A62: 45273 | B62: =A62 -> 45273 | C62: Manhã | D62: Idelfonso | E62: Missa | F62: 130 | H62: TRUE
D63: Neto | E63: Missa | F63: 150 | H63: TRUE
A64: 45274 | B64: =A64 -> 45274 | C64: Manhã | D64: Idelfonso | E64: Missa | F64: 130 | H64: TRUE
A65: 45275 | B65: =A65 -> 45275 | C65: Manhã | D65: Marcos | E65: Missa | F65: 150 | H65: TRUE
C66: Manhã | D66: Idelfonso | E66: Confissão | F66: 130 | H66: TRUE | K66: Total | L66: =SUM(L50:L65) -> 35 | M66: =SUM(M50:M65) -> 8 | N66: =SUM(N50:N65) -> 43 | O66: =SUM(O50:O65) -> 6520 | P66: =SUM(P50:P65) -> 6520 | Q66: =O66-P66 -> 0
A67: 45277 | B67: =A67 -> 45277 | C67: Manhã | D67: Josieldo | E67: Missa | F67: 200 | H67: TRUE
C68: Noite | D68: Ricardo Régis | E68: Missa | F68: 200 | H68: TRUE
A69: 45278 | B69: =A69 -> 45278 | C69: Manhã | D69: Idelfonso | E69: Missa | F69: 130 | H69: TRUE
A70: 45279 | B70: =A70 -> 45279 | C70: Manhã | D70: Marcos | E70: Missa | F70: 150 | H70: TRUE
C71: Manhã | D71: Idelfonso | E71: Confissão | F71: 130 | H71: TRUE
A72: 45280 | B72: =A72 -> 45280 | C72: Manhã | D72: Idelfonso | E72: Missa | F72: 130 | H72: TRUE
A73: 45281 | B73: =A73 -> 45281 | C73: Manhã | D73: Idelfonso | E73: Missa | F73: 130 | H73: TRUE
A74: 45282 | B74: =A74 -> 45282 | C74: Manhã | D74: Marcos | E74: Missa | F74: 150 | H74: TRUE
C75: Manhã | D75: Idelfonso | E75: Confissão | F75: 130 | H75: TRUE
A76: 45283 | B76: =A76 -> 45283 | C76: Noite | D76: Josieldo | E76: Missa | F76: 200 | H76: TRUE
A77: 45284 | B77: =A77 -> 45284 | C77: Manhã | D77: Josieldo | E77: Missa | F77: 200 | H77: TRUE
C78: Noite | D78: Josieldo | E78: Missa | F78: 200 | G78: Missa do Galo | H78: TRUE
A79: 45285 | B79: =A79 -> 45285 | C79: Noite | D79: Josieldo | E79: Missa | F79: 200 | H79: TRUE
A80: 45286 | B80: =A80 -> 45286 | C80: Manhã | D80: Marcos | E80: Missa | F80: 150 | H80: TRUE
C81: Manhã | D81: Idelfonso | E81: Confissão | F81: 130 | H81: TRUE
A82: 45287 | B82: =A82 -> 45287 | C82: Manhã | D82: Idelfonso | E82: Missa | F82: 130 | H82: TRUE
A83: 45288 | B83: =A83 -> 45288 | C83: Manhã | D83: Idelfonso | E83: Missa | F83: 130 | H83: TRUE
A84: 45289 | B84: =A84 -> 45289 | C84: Manhã | D84: Marcos | E84: Missa | F84: 150 | H84: TRUE
C85: Manhã | D85: Idelfonso | E85: Confissão | F85: 130 | H85: TRUE
A86: 45291 | B86: =A86 -> 45291 | C86: Manhã | D86: João Paulo | E86: Missa | F86: 200 | H86: TRUE
C87: Noite | D87: Edvânio | E87: Missa | F87: 200 | H87: TRUE
A88: Total | F88: =SUM(F45:F87) -> 6520
A89: Janeiro/2024
A90: 45292 | B90: =A90 -> 45292 | C90: Manhã | D90: Josieldo | E90: Missa | F90: 200 | H90: TRUE
A91: 45293 | B91: =A91 -> 45293 | C91: Manhã | D91: Willame | E91: Missa | F91: 150 | H91: TRUE
D92: Idelfonso | E92: Confissão | F92: 130 | H92: TRUE
A93: 45294 | B93: =A93 -> 45294 | C93: Manhã | D93: Idelfonso | E93: Missa | F93: 130 | H93: TRUE
A94: 45295 | B94: =A94 -> 45295 | C94: Manhã | D94: Idelfonso | E94: Missa | F94: 130 | H94: TRUE | K94: Resumo do mês Jan/2024 - Espórtulas
A95: 45296 | B95: =A95 -> 45296 | C95: Manhã | D95: Marcos | E95: Missa | F95: 150 | H95: TRUE | K95: Sacerdote | L95: Missa | M95: Confissão | N95: Total | O95: Total Previsto | P95: Total Realizado | Q95: Saldo a Pagar
C96: Manhã | D96: Idelfonso | E96: Confissão | F96: 130 | H96: TRUE | K96: Idelfonso | L96: =COUNTIFS($D$90:$D$133, $K96,$E$90:$E$133,$L$95) -> 13 | M96: =COUNTIFS($D$90:$D$133, $K96,$E$90:$E$133,$M$95) -> 9 | N96: =L96+M96 -> 22 | O96: =SUMIFS($F$90:$F$133,$D$90:$D$133,$K96) -> 2860 | P96: =SUMIFS($F$90:$F$133,$D$90:$D$133,$K96,$H$90:$H$133,TRUE) -> 2860 | Q96: =O96-P96 -> 0
C97: Noite | D97: Josieldo | E97: Missa | F97: 150 | G97: MIssa da família | H97: TRUE | K97: Josieldo | L97: =COUNTIFS($D$90:$D$133, $K97,$E$90:$E$133,$L$95) -> 7 | M97: =COUNTIFS($D$90:$D$133, $K97,$E$90:$E$133,$M$95) -> 0 | N97: =L97+M97 -> 7 | O97: =SUMIFS($F$90:$F$133,$D$90:$D$133,$K97) -> 1300 | P97: =SUMIFS($F$90:$F$133,$D$90:$D$133,$K97,$H$90:$H$133,TRUE) -> 1300 | Q97: =O97-P97 -> 0
A98: 45298 | B98: =A98 -> 45298 | C98: Manhã | D98: Josieldo | E98: Missa | F98: 200 | H98: TRUE | K98: Marcos | L98: =COUNTIFS($D$90:$D$133, $K98,$E$90:$E$133,$L$95) -> 7 | M98: =COUNTIFS($D$90:$D$133, $K98,$E$90:$E$133,$M$95) -> 0 | N98: =L98+M98 -> 7 | O98: =SUMIFS($F$90:$F$133,$D$90:$D$133,$K98) -> 1050 | P98: =SUMIFS($F$90:$F$133,$D$90:$D$133,$K98,$H$90:$H$133,TRUE) -> 1050 | Q98: =O98-P98 -> 0
C99: Noite | D99: Watson | E99: Missa | F99: 200 | H99: TRUE | K99: Raphael | L99: =COUNTIFS($D$90:$D$133, $K99,$E$90:$E$133,$L$95) -> 1 | M99: =COUNTIFS($D$90:$D$133, $K99,$E$90:$E$133,$M$95) -> 0 | N99: =L99+M99 -> 1 | O99: =SUMIFS($F$90:$F$133,$D$90:$D$133,$K99) -> 200 | P99: =SUMIFS($F$90:$F$133,$D$90:$D$133,$K99,$H$90:$H$133,TRUE) -> 200 | Q99: =O99-P99 -> 0
A100: 45299 | B100: =A100 -> 45299 | C100: Manhã | D100: Idelfonso | E100: Missa | F100: 130 | H100: TRUE | K100: Watson | L100: =COUNTIFS($D$90:$D$133, $K100,$E$90:$E$133,$L$95) -> 1 | M100: =COUNTIFS($D$90:$D$133, $K100,$E$90:$E$133,$M$95) -> 0 | N100: =L100+M100 -> 1 | O100: =SUMIFS($F$90:$F$133,$D$90:$D$133,$K100) -> 200 | P100: =SUMIFS($F$90:$F$133,$D$90:$D$133,$K100,$H$90:$H$133,TRUE) -> 200 | Q100: =O100-P100 -> 0
...

Sheet Limpeza
A1: aqui
A2: Abril/2026
A3: 46119 | B3: =A3 -> 46119 | C3: Maria José Marinho | D3: 170 | E3: TRUE | G3: Valor Pago
A4: 46121 | B4: =A4 -> 46121 | C4: Maria José Marinho | D4: 170 | E4: TRUE | G4: =SUMIF($E$1:$E$10, TRUE, $D$1:$D$10) -> 1360
A5: 46126 | B5: =A5 -> 46126 | C5: Maria José Marinho | D5: 170 | E5: TRUE
A6: 46128 | B6: =A6 -> 46128 | C6: Maria José Marinho | D6: 170 | E6: TRUE
A7: 46134 | B7: =A7 -> 46134 | C7: Maria José Marinho | D7: 170 | E7: TRUE | G7: Valor a Pagar
A8: 46135 | B8: =A8 -> 46135 | C8: Maria José Marinho | D8: 170 | E8: TRUE | G8: =D11-G4 -> 0
A9: 46140 | B9: =A9 -> 46140 | C9: Maria José Marinho | D9: 170 | E9: TRUE
A10: 46142 | B10: =A10 -> 46142 | C10: Maria José Marinho | D10: 170 | E10: TRUE
A11: Total | D11: =SUM(D3:D10) -> 1360
A13: Maio/2026
A14: 46147 | B14: =A14 -> 46147 | C14: Maria José Marinho | D14: 0 | E14: TRUE | F14: AUSENTE | G14: Valor Pago
A15: 46150 | B15: =A15 -> 46150 | C15: Maria José Marinho | D15: 170 | E15: TRUE | G15: =SUMIF($E$14:$E$21, TRUE, $D$14:$D$21) -> 1020
A16: 46155 | B16: =A16 -> 46155 | C16: Maria José Marinho | D16: 170 | E16: TRUE
A17: 46157 | B17: =A17 -> 46157 | C17: Maria José Marinho | D17: 170 | E17: TRUE
A18: 46162 | B18: =A18 -> 46162 | C18: Maria José Marinho | D18: 170 | E18: TRUE | G18: Valor a Pagar
A19: 46164 | B19: =A19 -> 46164 | C19: Maria José Marinho | D19: 170 | E19: TRUE | G19: =D22-G15 -> 170
A20: 46169 | B20: =A20 -> 46169 | C20: Maria José Marinho | D20: 170 | E20: TRUE
A21: 46170 | B21: =A21 -> 46170 | C21: Maria José Marinho | D21: 170 | E21: FALSE
A22: Total | D22: =SUM(D14:D21) -> 1190

Sheet Tabelas Básicas
A1: Itens de Consumo | E1: Sacerdotes | H1: Serviços | J1: Fornecedores
A2: Item | B2: Descrição | E2: André | H2: Missa | J2: Material | K2: Nome | L2: Endereço | M2: Bairro | N2: Fone | O2: Contato | P2: Observação
A3: 1 | B3: Bloco de recibos | E3: Arthur Ricardo | H3: Confissão | J3: Carvão (Tablete) | K3: Lojas Paulinas | L3: Av. Antonio Sales, 2919 | M3: Dionisio Torres | N3: (85) 998570146
A4: 2 | B4: Vinho | E4: Bessa | H4: Formação | J4: Vinho canônico | K4: Lojas Paulinas | L4: Av. Antonio Sales, 2919 | M4: Dionisio Torres | N4: (85) 998570146
A5: 3 | B5: Partículas | E5: Cosmo | H5: Diácono | J5: Diretório Litúrgico | K5: Lojas Paulinas | L5: Av. Antonio Sales, 2919 | M5: Dionisio Torres | N5: (85) 998570146
A6: 4 | B6: Água | E6: Deusimar | J6: Partículas Litúrgicas | K6: Mosteiro N.S. da Conceição | L6: Rua. Visconde do Rio Branco, 2590 | N6: (85) 32262038
A7: 5 | B7: Copos descartáveis ( 180 ml ) | E7: Diego Félix | J7: Vinho canônico | K7: Instituto das Filhas de São José | L7: Av. da Universidade, 3186 | M7: Damas | N7: (85) 3281.5135
A8: 6 | B8: Papel toalha | E8: Diego Juaçaba | H8: Anos | J8: Manga de vidro | K8: Lojas Vozes
A9: 7 | B9: Cheirinho ( anti-môfo) | E9: Douglas | H9: 2023 | J9: Manga de vidro | K9: Lojas Paulinas | L9: Av. Antonio Sales, 2919 | M9: Dionisio Torres | N9: (85) 998570146
A10: 8 | B10: Incenso | E10: Edvânio | H10: 2024 | J10: Manga de vidro | K10: Casa de Maria
A11: 9 | B11: Carvão Tablete | E11: Francisco Mota | H11: 2025 | J11: Alfaias Litúrgicas ( coporal e sanquíneo ) | K11: Lojas Paulinas | L11: Av. Antonio Sales, 2919 | M11: Dionisio Torres | N11: (85) 998570146
A12: 10 | B12: Velas ( Altar, Santíssimo e diárias ) | E12: Geilson | H12: 2026 | J12: Velas em geral | K12: Renna Luz | L12: Rua Julio Siqueira, 770 | M12: Dionisio Torres | N12: (85) 3257.2253 | P12: Já tem cadastro no CNJ 63.291.041/0001-02. Associação Face de Cristo.
A13: 11 | B13: Mangas vidro | E13: Geovani
A14: 12 | B14: Lavanderia | E14: Glailson
A15: 13 | B15: Lavagem das alfaias litúrgicas ( corporal e sanguíneo ) | E15: Gregório Paixão | H15: Limpeza | I15: Chave Pix
A16: 14 | B16: Limpeza da sacristia | E16: Haroldo | H16: Maria José Marinho | I16: 85 994154357
A17: 15 | B17: Material de limpeza | E17: Idelfonso
A18: 16 | B18: Acessórios sacristica | E18: Italo Dias
A19: 17 | B19: Chaveiro | E19: Ivan
E20: João Paulo
E21: Jocenilton
E22: Jorge Hermes
E23: Josieldo
E24: Marcos
E25: Não Identificado
E26: Nelson
E27: Neto
E28: Paulo Aniceto
E29: Raphael
E30: Ricardo Régis
E31: Roberto Guilhermino
... E54: Francisco José

Sheet Tapete Corpus Christi
A1: Ano | B1: Fornecedor | C1: Produto | D1: Qtde | E1: Un | F1: Valor Unitário | G1: Valor Total | H1: Observação
A2: 2024 | B2: Real Construções | C2: Tinta corante para o tapete | D2: 17 | E2: Tb | F2: 5 | G2: =D2*F2 -> 85
B3: Plásticos e Cia | C3: Sacolas para preparar a tintura do sal grosso | D3: 1 | E3: pct | F3: 5 | G3: 5
B4: Talimpo | C4: Luvas para usar no tapete | D4: 1 | E4: cx | F4: 29 | G4: 29 | H4: * 230 Kg de sal grosso recebido
B5: Plásticos e Cia | C5: Bacia descartável (embalagem) | D5: 3 | F5: 4.5 | G5: =D5*F5 -> 13.5 | H5: * 100 Kg de sal grosso utilizado
C6: 1 PCT Sacola reciclável | D6: 1 | F6: 5 | G6: =D6*F6 -> 5 | H6: * 130 Kg de sal grosso doado para RS
C7: 1 pct copo semi-acrílico | D7: 1 | F7: 13.5 | G7: =D7*F7 -> 13.5
C8: 1 pct colher descartável | D8: 1 | F8: 5.5 | G8: =D8*F8 -> 5.5
B9: Fortaleza Tintas | C9: 6 Corantes xadrez | D9: 10 | F9: 3.6 | G9: =D9*F9 -> 36
B10: Depósito Edvaldo | C10: 7 Corantes xadrez | D10: 7 | F10: 5 | G10: =D10*F10 -> 35
B11: Mormaço | C11: Tinta 250 ml | D11: 2 | F11: 9.53 | G11: =D11*F11 -> 19.06
C12: Tinta metálica | D12: 1 | F12: 22.43 | G12: =D12*F12 -> 22.43
B13: Talimpo | C13: Luvas procedimento | D13: 1 | E13: cx | F13: 38.1 | G13: 38.1
B14: Total | G14: =SUM(G2:G13) -> 307.09

Sheet Plano de Contas
A1: Entradas
A7: Saídas
C8: 1 | D8: Bloco de recibos
C9: 2 | D9: Vinho
C10: 3 | D10: Partículas
C11: 4 | D11: Água
C12: 5 | D12: Copos descartáveis ( 180 ml )
C13: 6 | D13: Papel toalha
C14: 7 | D14: Cheirinho ( anti-môfo)
C15: 8 | D15: Incenso
C16: 9 | D16: Carvão Tablete
C17: 10 | D17: Velas ( Altar, Santíssimo e diárias )
C18: 11 | D18: Mangas vidro
C19: 12 | D19: Lavanderia
... C24: 17 | D24: Chaveiro
